{
"meta":{"test_sets":[],"test_metrics":[],"learn_metrics":[{"best_value":"Min","name":"RMSE"}],"launch_mode":"Train","parameters":"","iteration_count":1000,"learn_sets":["learn"],"name":"experiment"},
"iterations":[
{"learn":[14.59871775],"iteration":0,"passed_time":0.0007521953626,"remaining_time":0.7514431672},
{"learn":[14.22518863],"iteration":1,"passed_time":0.0014143329,"remaining_time":0.7057521169},
{"learn":[13.8866124],"iteration":2,"passed_time":0.002102342685,"remaining_time":0.6986785522},
{"learn":[13.52356875],"iteration":3,"passed_time":0.002756039488,"remaining_time":0.6862538326},
{"learn":[13.18870211],"iteration":4,"passed_time":0.003427807599,"remaining_time":0.6821337122},
{"learn":[12.9124226],"iteration":5,"passed_time":0.004004397702,"remaining_time":0.6633952193},
{"learn":[12.60003351],"iteration":6,"passed_time":0.00456903703,"remaining_time":0.6481505387},
{"learn":[12.32990573],"iteration":7,"passed_time":0.005139076564,"remaining_time":0.6372454939},
{"learn":[12.0660619],"iteration":8,"passed_time":0.005694484827,"remaining_time":0.6270260515},
{"learn":[11.77309809],"iteration":9,"passed_time":0.006290666369,"remaining_time":0.6227759705},
{"learn":[11.49227636],"iteration":10,"passed_time":0.006842654335,"remaining_time":0.6152168306},
{"learn":[11.26264833],"iteration":11,"passed_time":0.00744201668,"remaining_time":0.61272604},
{"learn":[11.04260393],"iteration":12,"passed_time":0.008181550942,"remaining_time":0.6211685215},
{"learn":[10.79916926],"iteration":13,"passed_time":0.00880564491,"remaining_time":0.6201689915},
{"learn":[10.5541002],"iteration":14,"passed_time":0.009399616787,"remaining_time":0.6172415023},
{"learn":[10.31918115],"iteration":15,"passed_time":0.01001999043,"remaining_time":0.6162294115},
{"learn":[10.10004441],"iteration":16,"passed_time":0.01056212754,"remaining_time":0.6107394925},
{"learn":[9.894556723],"iteration":17,"passed_time":0.01117695123,"remaining_time":0.6097647838},
{"learn":[9.690174082],"iteration":18,"passed_time":0.01172430879,"remaining_time":0.605344575},
{"learn":[9.506034866],"iteration":19,"passed_time":0.01227197638,"remaining_time":0.6013268428},
{"learn":[9.338524633],"iteration":20,"passed_time":0.01282531447,"remaining_time":0.5979039458},
{"learn":[9.170203312],"iteration":21,"passed_time":0.0134236662,"remaining_time":0.5967429791},
{"learn":[9.010299969],"iteration":22,"passed_time":0.01396410316,"remaining_time":0.5931708168},
{"learn":[8.843866678],"iteration":23,"passed_time":0.01454638402,"remaining_time":0.5915529501},
{"learn":[8.690548059],"iteration":24,"passed_time":0.01509195143,"remaining_time":0.5885861056},
{"learn":[8.555307687],"iteration":25,"passed_time":0.01567199157,"remaining_time":0.5870969148},
{"learn":[8.413851302],"iteration":26,"passed_time":0.01620780813,"remaining_time":0.5840813818},
{"learn":[8.29256019],"iteration":27,"passed_time":0.01673298376,"remaining_time":0.5808735792},
{"learn":[8.162193833],"iteration":28,"passed_time":0.01730845377,"remaining_time":0.5795347796},
{"learn":[8.040736294],"iteration":29,"passed_time":0.01783485951,"remaining_time":0.5766604575},
{"learn":[7.921220278],"iteration":30,"passed_time":0.01839641831,"remaining_time":0.5750364303},
{"learn":[7.809589039],"iteration":31,"passed_time":0.01893038471,"remaining_time":0.5726441374},
{"learn":[7.699675801],"iteration":32,"passed_time":0.01957028057,"remaining_time":0.5734685247},
{"learn":[7.60645267],"iteration":33,"passed_time":0.02012208852,"remaining_time":0.5717040445},
{"learn":[7.498880302],"iteration":34,"passed_time":0.0208087982,"remaining_time":0.5737282931},
{"learn":[7.401158744],"iteration":35,"passed_time":0.02139288869,"remaining_time":0.5728540193},
{"learn":[7.306431077],"iteration":36,"passed_time":0.02200507215,"remaining_time":0.5727266075},
{"learn":[7.223863468],"iteration":37,"passed_time":0.02261580495,"remaining_time":0.572536957},
{"learn":[7.143477682],"iteration":38,"passed_time":0.02325234027,"remaining_time":0.5729615127},
{"learn":[7.062817131],"iteration":39,"passed_time":0.02383441111,"remaining_time":0.5720258666},
{"learn":[6.990793435],"iteration":40,"passed_time":0.02441816184,"remaining_time":0.571146761},
{"learn":[6.931862224],"iteration":41,"passed_time":0.02500735277,"remaining_time":0.5704058084},
{"learn":[6.858296558],"iteration":42,"passed_time":0.02560025455,"remaining_time":0.5697545025},
{"learn":[6.786268161],"iteration":43,"passed_time":0.02616649376,"remaining_time":0.5685265462},
{"learn":[6.717118549],"iteration":44,"passed_time":0.02671078105,"remaining_time":0.5668621313},
{"learn":[6.652948106],"iteration":45,"passed_time":0.02728974136,"remaining_time":0.5659655057},
{"learn":[6.589686076],"iteration":46,"passed_time":0.02787058157,"remaining_time":0.5651205157},
{"learn":[6.531283097],"iteration":47,"passed_time":0.0284232596,"remaining_time":0.563727982},
{"learn":[6.471368031],"iteration":48,"passed_time":0.02904067378,"remaining_time":0.563626138},
{"learn":[6.416481395],"iteration":49,"passed_time":0.0296826793,"remaining_time":0.5639709067},
{"learn":[6.369870822],"iteration":50,"passed_time":0.03025941915,"remaining_time":0.563062525},
{"learn":[6.325678067],"iteration":51,"passed_time":0.03079665584,"remaining_time":0.5614467256},
{"learn":[6.275766122],"iteration":52,"passed_time":0.0315113582,"remaining_time":0.5630425702},
{"learn":[6.224773967],"iteration":53,"passed_time":0.03208892839,"remaining_time":0.5621504863},
{"learn":[6.182249254],"iteration":54,"passed_time":0.03271012237,"remaining_time":0.5620193753},
{"learn":[6.139904173],"iteration":55,"passed_time":0.03335353828,"remaining_time":0.5622453596},
{"learn":[6.100525536],"iteration":56,"passed_time":0.0339184171,"remaining_time":0.5611415321},
{"learn":[6.062568564],"iteration":57,"passed_time":0.03445532376,"remaining_time":0.5596019824},
{"learn":[6.030559288],"iteration":58,"passed_time":0.03500895187,"remaining_time":0.5583631137},
{"learn":[5.997931376],"iteration":59,"passed_time":0.03570527237,"remaining_time":0.5593826005},
{"learn":[5.964103835],"iteration":60,"passed_time":0.03624381917,"remaining_time":0.5579171509},
{"learn":[5.933729724],"iteration":61,"passed_time":0.0368154091,"remaining_time":0.5569815119},
{"learn":[5.901932711],"iteration":62,"passed_time":0.03745337454,"remaining_time":0.557044634},
{"learn":[5.873727795],"iteration":63,"passed_time":0.03799431155,"remaining_time":0.5556668063},
{"learn":[5.846485734],"iteration":64,"passed_time":0.03851302662,"remaining_time":0.5539950752},
{"learn":[5.820630862],"iteration":65,"passed_time":0.03904867316,"remaining_time":0.5525978899},
{"learn":[5.793646238],"iteration":66,"passed_time":0.03956910839,"remaining_time":0.5510145989},
{"learn":[5.765388646],"iteration":67,"passed_time":0.04009136377,"remaining_time":0.5494875152},
{"learn":[5.747073912],"iteration":68,"passed_time":0.04061371916,"remaining_time":0.5479909064},
{"learn":[5.722315217],"iteration":69,"passed_time":0.04111403264,"remaining_time":0.5462292907},
{"learn":[5.699970599],"iteration":70,"passed_time":0.04162085668,"remaining_time":0.5445883923},
{"learn":[5.682732647],"iteration":71,"passed_time":0.0421700344,"remaining_time":0.5435248878},
{"learn":[5.663525791],"iteration":72,"passed_time":0.04267479826,"remaining_time":0.5419114793},
{"learn":[5.642381613],"iteration":73,"passed_time":0.04317019131,"remaining_time":0.5402107723},
{"learn":[5.621404779],"iteration":74,"passed_time":0.04367481516,"remaining_time":0.5386560536},
{"learn":[5.602460129],"iteration":75,"passed_time":0.04420937161,"remaining_time":0.5374928864},
{"learn":[5.587337574],"iteration":76,"passed_time":0.04470210442,"remaining_time":0.5358447063},
{"learn":[5.572393026],"iteration":77,"passed_time":0.04518717657,"remaining_time":0.5341356},
{"learn":[5.558425806],"iteration":78,"passed_time":0.04570394148,"remaining_time":0.5328269633},
{"learn":[5.541518902],"iteration":79,"passed_time":0.0462208664,"remaining_time":0.5315399636},
{"learn":[5.526157283],"iteration":80,"passed_time":0.04673562113,"remaining_time":0.5302473558},
{"learn":[5.511746977],"iteration":81,"passed_time":0.04723447448,"remaining_time":0.5287957021},
{"learn":[5.504975022],"iteration":82,"passed_time":0.04756834349,"remaining_time":0.5255442287},
{"learn":[5.493980522],"iteration":83,"passed_time":0.04811022057,"remaining_time":0.5246305006},
{"learn":[5.480745463],"iteration":84,"passed_time":0.04860367345,"remaining_time":0.5232042495},
{"learn":[5.464052013],"iteration":85,"passed_time":0.04916266203,"remaining_time":0.5224961988},
{"learn":[5.449143727],"iteration":86,"passed_time":0.04967366643,"remaining_time":0.5212880167},
{"learn":[5.438255432],"iteration":87,"passed_time":0.05019785198,"remaining_time":0.5202322842},
{"learn":[5.425927931],"iteration":88,"passed_time":0.05069742539,"remaining_time":0.5189365678},
{"learn":[5.412331217],"iteration":89,"passed_time":0.05124426291,"remaining_time":0.5181364361},
{"learn":[5.400691499],"iteration":90,"passed_time":0.05175372718,"remaining_time":0.5169685495},
{"learn":[5.391618744],"iteration":91,"passed_time":0.05221496726,"remaining_time":0.5153390247},
{"learn":[5.380766572],"iteration":92,"passed_time":0.05267829752,"remaining_time":0.5137550092},
{"learn":[5.372207183],"iteration":93,"passed_time":0.0531728605,"remaining_time":0.5124958682},
{"learn":[5.362918837],"iteration":94,"passed_time":0.05365767263,"remaining_time":0.511159934},
{"learn":[5.348292324],"iteration":95,"passed_time":0.05413360398,"remaining_time":0.5097581042},
{"learn":[5.339772295],"iteration":96,"passed_time":0.05459928445,"remaining_time":0.5082799367},
{"learn":[5.331515983],"iteration":97,"passed_time":0.05507469576,"remaining_time":0.5069119957},
{"learn":[5.323861644],"iteration":98,"passed_time":0.05553599584,"remaining_time":0.5054336591},
{"learn":[5.313277281],"iteration":99,"passed_time":0.0560004462,"remaining_time":0.5040040158},
{"learn":[5.30685627],"iteration":100,"passed_time":0.0564607962,"remaining_time":0.502556988},
{"learn":[5.29652059],"iteration":101,"passed_time":0.05692356642,"remaining_time":0.5011506141},
{"learn":[5.288350766],"iteration":102,"passed_time":0.05739871771,"remaining_time":0.4998703862},
{"learn":[5.27993346],"iteration":103,"passed_time":0.05786728842,"remaining_time":0.4985489464},
{"learn":[5.271789139],"iteration":104,"passed_time":0.05835234057,"remaining_time":0.4973842363},
{"learn":[5.262684686],"iteration":105,"passed_time":0.05883690268,"remaining_time":0.4962282169},
{"learn":[5.251619772],"iteration":106,"passed_time":0.05935180742,"remaining_time":0.4953379816},
{"learn":[5.241012171],"iteration":107,"passed_time":0.05983765964,"remaining_time":0.4942147444},
{"learn":[5.232684032],"iteration":108,"passed_time":0.0603205316,"remaining_time":0.4930788409},
{"learn":[5.224267141],"iteration":109,"passed_time":0.06078588204,"remaining_time":0.4918130456},
{"learn":[5.216324968],"iteration":110,"passed_time":0.061245772,"remaining_time":0.4905179397},
{"learn":[5.211102527],"iteration":111,"passed_time":0.0617498058,"remaining_time":0.489587746},
{"learn":[5.206364257],"iteration":112,"passed_time":0.06226970097,"remaining_time":0.4887895997},
{"learn":[5.196937641],"iteration":113,"passed_time":0.06274910263,"remaining_time":0.4876816222},
{"learn":[5.190746047],"iteration":114,"passed_time":0.06322759421,"remaining_time":0.4865775728},
{"learn":[5.181885213],"iteration":115,"passed_time":0.06370347556,"remaining_time":0.4854644172},
{"learn":[5.178293568],"iteration":116,"passed_time":0.06408539875,"remaining_time":0.4836530521},
{"learn":[5.170991438],"iteration":117,"passed_time":0.0645704909,"remaining_time":0.4826370591},
{"learn":[5.166257212],"iteration":118,"passed_time":0.06504390204,"remaining_time":0.4815435101},
{"learn":[5.161421246],"iteration":119,"passed_time":0.06550357198,"remaining_time":0.4803595279},
{"learn":[5.158223542],"iteration":120,"passed_time":0.06598963422,"remaining_time":0.4793792436},
{"learn":[5.15470988],"iteration":121,"passed_time":0.06636411676,"remaining_time":0.4776040534},
{"learn":[5.146388143],"iteration":122,"passed_time":0.06683840798,"remaining_time":0.4765632829},
{"learn":[5.139529364],"iteration":123,"passed_time":0.06731318923,"remaining_time":0.475535111},
{"learn":[5.134276023],"iteration":124,"passed_time":0.06778475021,"remaining_time":0.4744932515},
{"learn":[5.128536065],"iteration":125,"passed_time":0.06828127335,"remaining_time":0.4736335945},
{"learn":[5.123300353],"iteration":126,"passed_time":0.06867270737,"remaining_time":0.4720572719},
{"learn":[5.116200518],"iteration":127,"passed_time":0.06915688944,"remaining_time":0.4711313093},
{"learn":[5.108728704],"iteration":128,"passed_time":0.06965736293,"remaining_time":0.4703221947},
{"learn":[5.104075866],"iteration":129,"passed_time":0.07012594365,"remaining_time":0.4693043921},
{"learn":[5.100317606],"iteration":130,"passed_time":0.07056902215,"remaining_time":0.4681258034},
{"learn":[5.095814182],"iteration":131,"passed_time":0.07103195238,"remaining_time":0.467088899},
{"learn":[5.092146915],"iteration":132,"passed_time":0.07147661102,"remaining_time":0.4659415169},
{"learn":[5.085258329],"iteration":133,"passed_time":0.07193361073,"remaining_time":0.4648843798},
{"learn":[5.079219421],"iteration":134,"passed_time":0.0723936507,"remaining_time":0.4638556138},
{"learn":[5.076476829],"iteration":135,"passed_time":0.07283886939,"remaining_time":0.4627410526},
{"learn":[5.072133867],"iteration":136,"passed_time":0.0732901086,"remaining_time":0.4616741878},
{"learn":[5.067031564],"iteration":137,"passed_time":0.07374411805,"remaining_time":0.460633549},
{"learn":[5.061358312],"iteration":138,"passed_time":0.07419879756,"remaining_time":0.4596055014},
{"learn":[5.056759124],"iteration":139,"passed_time":0.07466140776,"remaining_time":0.458634362},
{"learn":[5.050254],"iteration":140,"passed_time":0.07512575811,"remaining_time":0.457681037},
{"learn":[5.048376474],"iteration":141,"passed_time":0.07543660512,"remaining_time":0.4558070929},
{"learn":[5.042603751],"iteration":142,"passed_time":0.07592181729,"remaining_time":0.4549999819},
{"learn":[5.037477349],"iteration":143,"passed_time":0.07644948314,"remaining_time":0.4544497053},
{"learn":[5.03230489],"iteration":144,"passed_time":0.07698357955,"remaining_time":0.4539376587},
{"learn":[5.025976187],"iteration":145,"passed_time":0.07747196199,"remaining_time":0.4531579146},
{"learn":[5.01952451],"iteration":146,"passed_time":0.07799135712,"remaining_time":0.4525620927},
{"learn":[5.017569424],"iteration":147,"passed_time":0.07847458911,"remaining_time":0.4517591211},
{"learn":[5.008962367],"iteration":148,"passed_time":0.0789612214,"remaining_time":0.4509798618},
{"learn":[5.003880266],"iteration":149,"passed_time":0.07945228407,"remaining_time":0.4502296097},
{"learn":[4.996387564],"iteration":150,"passed_time":0.07993659615,"remaining_time":0.4494448353},
{"learn":[4.993361683],"iteration":151,"passed_time":0.08040854716,"remaining_time":0.4485950526},
{"learn":[4.99005752],"iteration":152,"passed_time":0.08086896717,"remaining_time":0.4476863738},
{"learn":[4.986908764],"iteration":153,"passed_time":0.08133846797,"remaining_time":0.446833402},
{"learn":[4.985207175],"iteration":154,"passed_time":0.08181146907,"remaining_time":0.4460044604},
{"learn":[4.979003494],"iteration":155,"passed_time":0.08232592351,"remaining_time":0.4454043554},
{"learn":[4.973142217],"iteration":156,"passed_time":0.08280272494,"remaining_time":0.4446031664},
{"learn":[4.967056696],"iteration":157,"passed_time":0.08328565691,"remaining_time":0.4438387539},
{"learn":[4.961460696],"iteration":158,"passed_time":0.08376178828,"remaining_time":0.4430419116},
{"learn":[4.954240363],"iteration":159,"passed_time":0.0842314891,"remaining_time":0.4422153178},
{"learn":[4.952320707],"iteration":160,"passed_time":0.08454270614,"remaining_time":0.4405672699},
{"learn":[4.948337777],"iteration":161,"passed_time":0.0849990958,"remaining_time":0.4396866807},
{"learn":[4.943228639],"iteration":162,"passed_time":0.08545930579,"remaining_time":0.4388309138},
{"learn":[4.938545759],"iteration":163,"passed_time":0.08591224515,"remaining_time":0.4379429082},
{"learn":[4.935330572],"iteration":164,"passed_time":0.08635720381,"remaining_time":0.437019789},
{"learn":[4.932051543],"iteration":165,"passed_time":0.08682340432,"remaining_time":0.4362091518},
{"learn":[4.928964153],"iteration":166,"passed_time":0.08726807296,"remaining_time":0.4352952382},
{"learn":[4.922860227],"iteration":167,"passed_time":0.08771376169,"remaining_time":0.4343919627},
{"learn":[4.917668772],"iteration":168,"passed_time":0.08816524092,"remaining_time":0.4335225752},
{"learn":[4.910365386],"iteration":169,"passed_time":0.08863811201,"remaining_time":0.4327625469},
{"learn":[4.906457206],"iteration":170,"passed_time":0.08911909381,"remaining_time":0.4320451975},
{"learn":[4.901996508],"iteration":171,"passed_time":0.08959069479,"remaining_time":0.4312854377},
{"learn":[4.896816173],"iteration":172,"passed_time":0.09038562413,"remaining_time":0.432074631},
{"learn":[4.891123132],"iteration":173,"passed_time":0.09103026015,"remaining_time":0.4321321545},
{"learn":[4.887630202],"iteration":174,"passed_time":0.09157657762,"remaining_time":0.4317181516},
{"learn":[4.885259712],"iteration":175,"passed_time":0.09205219895,"remaining_time":0.4309716587},
{"learn":[4.880659728],"iteration":176,"passed_time":0.0925269602,"remaining_time":0.4302242274},
{"learn":[4.877299723],"iteration":177,"passed_time":0.09298460997,"remaining_time":0.4294008393},
{"learn":[4.874038772],"iteration":178,"passed_time":0.09344682013,"remaining_time":0.4286024544},
{"learn":[4.86943698],"iteration":179,"passed_time":0.09390374984,"remaining_time":0.4277837493},
{"learn":[4.861268711],"iteration":180,"passed_time":0.09436955032,"remaining_time":0.4270091807},
{"learn":[4.858673056],"iteration":181,"passed_time":0.09482684005,"remaining_time":0.4261997536},
{"learn":[4.854036207],"iteration":182,"passed_time":0.09528736007,"remaining_time":0.4254085966},
{"learn":[4.85130244],"iteration":183,"passed_time":0.0957422896,"remaining_time":0.4245962408},
{"learn":[4.847510084],"iteration":184,"passed_time":0.09618456803,"remaining_time":0.4237320159},
{"learn":[4.845691673],"iteration":185,"passed_time":0.09663236694,"remaining_time":0.4228964876},
{"learn":[4.842058646],"iteration":186,"passed_time":0.09708598636,"remaining_time":0.4220904113},
{"learn":[4.838623675],"iteration":187,"passed_time":0.09755665726,"remaining_time":0.4213617324},
{"learn":[4.834602161],"iteration":188,"passed_time":0.0980220577,"remaining_time":0.4206131682},
{"learn":[4.830858976],"iteration":189,"passed_time":0.09848023752,"remaining_time":0.419836802},
{"learn":[4.827590511],"iteration":190,"passed_time":0.09893323688,"remaining_time":0.4190418253},
{"learn":[4.822246226],"iteration":191,"passed_time":0.09938711632,"remaining_time":0.4182541145},
{"learn":[4.816686395],"iteration":192,"passed_time":0.09984058573,"remaining_time":0.4174681486},
{"learn":[4.814797121],"iteration":193,"passed_time":0.1002933151,"remaining_time":0.4166825358},
{"learn":[4.811639392],"iteration":194,"passed_time":0.1008194008,"remaining_time":0.4162031673},
{"learn":[4.804813432],"iteration":195,"passed_time":0.1013463066,"remaining_time":0.4157266861},
{"learn":[4.80251613],"iteration":196,"passed_time":0.1020096742,"remaining_time":0.4158059309},
{"learn":[4.800087884],"iteration":197,"passed_time":0.1024944463,"remaining_time":0.4151542725},
{"learn":[4.794773135],"iteration":198,"passed_time":0.1029529162,"remaining_time":0.4143984214},
{"learn":[4.791664833],"iteration":199,"passed_time":0.1033990849,"remaining_time":0.4135963398},
{"learn":[4.785989873],"iteration":200,"passed_time":0.1038778165,"remaining_time":0.4129272409},
{"learn":[4.782387142],"iteration":201,"passed_time":0.1043607185,"remaining_time":0.4122765018},
{"learn":[4.778623704],"iteration":202,"passed_time":0.1049340583,"remaining_time":0.4119824852},
{"learn":[4.775772178],"iteration":203,"passed_time":0.1054727551,"remaining_time":0.4115505544},
{"learn":[4.77023101],"iteration":204,"passed_time":0.106012332,"remaining_time":0.4111209949},
{"learn":[4.764496689],"iteration":205,"passed_time":0.1065312071,"remaining_time":0.410610575},
{"learn":[4.763138716],"iteration":206,"passed_time":0.1070395213,"remaining_time":0.4100596153},
{"learn":[4.758053283],"iteration":207,"passed_time":0.1075377746,"remaining_time":0.409470757},
{"learn":[4.755063788],"iteration":208,"passed_time":0.108026027,"remaining_time":0.4088449156},
{"learn":[4.752465267],"iteration":209,"passed_time":0.1085241003,"remaining_time":0.4082573296},
{"learn":[4.748067377],"iteration":210,"passed_time":0.1090203334,"remaining_time":0.4076637112},
{"learn":[4.744163298],"iteration":211,"passed_time":0.1094981949,"remaining_time":0.4070027246},
{"learn":[4.736670896],"iteration":212,"passed_time":0.1099796568,"remaining_time":0.40635676},
{"learn":[4.73349255],"iteration":213,"passed_time":0.1104502577,"remaining_time":0.4056724417},
{"learn":[4.731864595],"iteration":214,"passed_time":0.1109123178,"remaining_time":0.4049589278},
{"learn":[4.728398311],"iteration":215,"passed_time":0.111375288,"remaining_time":0.4042510455},
{"learn":[4.723865975],"iteration":216,"passed_time":0.1118559898,"remaining_time":0.403609401},
{"learn":[4.723483365],"iteration":217,"passed_time":0.1123016185,"remaining_time":0.4028434206},
{"learn":[4.72095416],"iteration":218,"passed_time":0.1128417452,"remaining_time":0.4024173653},
{"learn":[4.716173382],"iteration":219,"passed_time":0.1133454792,"remaining_time":0.4018612446},
{"learn":[4.710563974],"iteration":220,"passed_time":0.113872525,"remaining_time":0.4013877693},
{"learn":[4.707160263],"iteration":221,"passed_time":0.1143776889,"remaining_time":0.4008371261},
{"learn":[4.70408351],"iteration":222,"passed_time":0.1148928137,"remaining_time":0.4003215975},
{"learn":[4.702501831],"iteration":223,"passed_time":0.1154268401,"remaining_time":0.3998715532},
{"learn":[4.700269738],"iteration":224,"passed_time":0.115992679,"remaining_time":0.3995303388},
{"learn":[4.695346302],"iteration":225,"passed_time":0.1164824116,"remaining_time":0.3989264892},
{"learn":[4.689769299],"iteration":226,"passed_time":0.1169739743,"remaining_time":0.3983298772},
{"learn":[4.687919514],"iteration":227,"passed_time":0.1174794785,"remaining_time":0.397781392},
{"learn":[4.682982074],"iteration":228,"passed_time":0.1180392268,"remaining_time":0.3974159122},
{"learn":[4.679578702],"iteration":229,"passed_time":0.1185205787,"remaining_time":0.3967862851},
{"learn":[4.675751423],"iteration":230,"passed_time":0.1190929984,"remaining_time":0.3964611073},
{"learn":[4.672710726],"iteration":231,"passed_time":0.1195870413,"remaining_time":0.3958743438},
{"learn":[4.6690533],"iteration":232,"passed_time":0.1200756938,"remaining_time":0.3952706315},
{"learn":[4.667595702],"iteration":233,"passed_time":0.1205466347,"remaining_time":0.3946099239},
{"learn":[4.664241291],"iteration":234,"passed_time":0.1210225261,"remaining_time":0.3939669466},
{"learn":[4.662246999],"iteration":235,"passed_time":0.1215028978,"remaining_time":0.3933398896},
{"learn":[4.658668443],"iteration":236,"passed_time":0.1219694784,"remaining_time":0.3926696709},
{"learn":[4.658017572],"iteration":237,"passed_time":0.1224310385,"remaining_time":0.3919850896},
{"learn":[4.657656705],"iteration":238,"passed_time":0.1228895283,"remaining_time":0.3912925985},
{"learn":[4.653242871],"iteration":239,"passed_time":0.1233669198,"remaining_time":0.3906619127},
{"learn":[4.6507302],"iteration":240,"passed_time":0.1238390808,"remaining_time":0.3900160263},
{"learn":[4.647671336],"iteration":241,"passed_time":0.1243158323,"remaining_time":0.3893859539},
{"learn":[4.645506007],"iteration":242,"passed_time":0.1249035836,"remaining_time":0.3891029333},
{"learn":[4.641297906],"iteration":243,"passed_time":0.1254204385,"remaining_time":0.3885977521},
{"learn":[4.63798107],"iteration":244,"passed_time":0.1259180817,"remaining_time":0.3880332723},
{"learn":[4.635062318],"iteration":245,"passed_time":0.1264189753,"remaining_time":0.3874792982},
{"learn":[4.631606017],"iteration":246,"passed_time":0.1268959167,"remaining_time":0.386852734},
{"learn":[4.630215494],"iteration":247,"passed_time":0.1273664376,"remaining_time":0.3862079076},
{"learn":[4.62729814],"iteration":248,"passed_time":0.1278413489,"remaining_time":0.3855777229},
{"learn":[4.624691756],"iteration":249,"passed_time":0.1283243008,"remaining_time":0.3849729025},
{"learn":[4.621840053],"iteration":250,"passed_time":0.1288011323,"remaining_time":0.3843507891},
{"learn":[4.619602091],"iteration":251,"passed_time":0.1292524315,"remaining_time":0.3836540427},
{"learn":[4.613584029],"iteration":252,"passed_time":0.1297155917,"remaining_time":0.382994257},
{"learn":[4.6119388],"iteration":253,"passed_time":0.1301633206,"remaining_time":0.3822906976},
{"learn":[4.60870702],"iteration":254,"passed_time":0.1306217505,"remaining_time":0.3816204083},
{"learn":[4.604771557],"iteration":255,"passed_time":0.1310790902,"remaining_time":0.3809486059},
{"learn":[4.604231277],"iteration":256,"passed_time":0.1315442106,"remaining_time":0.3803009669},
{"learn":[4.600750354],"iteration":257,"passed_time":0.1320178618,"remaining_time":0.3796792769},
{"learn":[4.596488253],"iteration":258,"passed_time":0.132469361,"remaining_time":0.3789953534},
{"learn":[4.59470784],"iteration":259,"passed_time":0.1330015073,"remaining_time":0.3785427515},
{"learn":[4.588818005],"iteration":260,"passed_time":0.1334864294,"remaining_time":0.3779558289},
{"learn":[4.585054174],"iteration":261,"passed_time":0.13395332,"remaining_time":0.3773188937},
{"learn":[4.581471435],"iteration":262,"passed_time":0.1344185204,"remaining_time":0.3766785153},
{"learn":[4.577555199],"iteration":263,"passed_time":0.1348838508,"remaining_time":0.3760398266},
{"learn":[4.57457145],"iteration":264,"passed_time":0.1353535317,"remaining_time":0.3754145123},
{"learn":[4.573029224],"iteration":265,"passed_time":0.1358049909,"remaining_time":0.3747400876},
{"learn":[4.571326203],"iteration":266,"passed_time":0.1362963836,"remaining_time":0.3741769632},
{"learn":[4.571019224],"iteration":267,"passed_time":0.1367912266,"remaining_time":0.373623798},
{"learn":[4.565766631],"iteration":268,"passed_time":0.1372752086,"remaining_time":0.3730415521},
{"learn":[4.563383471],"iteration":269,"passed_time":0.1377646212,"remaining_time":0.3724747165},
{"learn":[4.558165805],"iteration":270,"passed_time":0.1382733554,"remaining_time":0.3719604283},
{"learn":[4.55629209],"iteration":271,"passed_time":0.1387920904,"remaining_time":0.371472948},
{"learn":[4.549383848],"iteration":272,"passed_time":0.1392848633,"remaining_time":0.3709161011},
{"learn":[4.546227503],"iteration":273,"passed_time":0.1397694354,"remaining_time":0.370337993},
{"learn":[4.540620977],"iteration":274,"passed_time":0.1402522573,"remaining_time":0.3697559511},
{"learn":[4.532898237],"iteration":275,"passed_time":0.1407302389,"remaining_time":0.3691619309},
{"learn":[4.529757367],"iteration":276,"passed_time":0.1412165011,"remaining_time":0.3685903621},
{"learn":[4.52579294],"iteration":277,"passed_time":0.1416860019,"remaining_time":0.3679758755},
{"learn":[4.521572155],"iteration":278,"passed_time":0.1421805049,"remaining_time":0.3674270395},
{"learn":[4.518818099],"iteration":279,"passed_time":0.1426626768,"remaining_time":0.3668468832},
{"learn":[4.514012334],"iteration":280,"passed_time":0.1431522493,"remaining_time":0.3662863604},
{"learn":[4.508331416],"iteration":281,"passed_time":0.1436222502,"remaining_time":0.3656765093},
{"learn":[4.506038537],"iteration":282,"passed_time":0.1441068523,"remaining_time":0.3651046399},
{"learn":[4.505805643],"iteration":283,"passed_time":0.144575963,"remaining_time":0.3644943294},
{"learn":[4.501550352],"iteration":284,"passed_time":0.1450897877,"remaining_time":0.3639971867},
{"learn":[4.494692643],"iteration":285,"passed_time":0.1455890711,"remaining_time":0.363463625},
{"learn":[4.489330245],"iteration":286,"passed_time":0.1460832038,"remaining_time":0.3629175062},
{"learn":[4.484826955],"iteration":287,"passed_time":0.1465641455,"remaining_time":0.3623391376},
{"learn":[4.478285428],"iteration":288,"passed_time":0.1471569473,"remaining_time":0.362036642},
{"learn":[4.475311671],"iteration":289,"passed_time":0.1476778826,"remaining_time":0.3615561953},
{"learn":[4.471581298],"iteration":290,"passed_time":0.1481682552,"remaining_time":0.3610010066},
{"learn":[4.469164956],"iteration":291,"passed_time":0.148706362,"remaining_time":0.3605620009},
{"learn":[4.462068024],"iteration":292,"passed_time":0.1492117859,"remaining_time":0.360043456},
{"learn":[4.458540976],"iteration":293,"passed_time":0.1497019085,"remaining_time":0.3594882564},
{"learn":[4.455757458],"iteration":294,"passed_time":0.1501867406,"remaining_time":0.3589208546},
{"learn":[4.453027414],"iteration":295,"passed_time":0.1506643721,"remaining_time":0.358336885},
{"learn":[4.450659338],"iteration":296,"passed_time":0.1511592951,"remaining_time":0.3577945605},
{"learn":[4.444696901],"iteration":297,"passed_time":0.1516597386,"remaining_time":0.3572655587},
{"learn":[4.442052813],"iteration":298,"passed_time":0.1522124164,"remaining_time":0.3568592102},
{"learn":[4.440036756],"iteration":299,"passed_time":0.1527054895,"remaining_time":0.3563128087},
{"learn":[4.435017051],"iteration":300,"passed_time":0.1532274548,"remaining_time":0.3558338569},
{"learn":[4.429962125],"iteration":301,"passed_time":0.1537210177,"remaining_time":0.3552889747},
{"learn":[4.427666256],"iteration":302,"passed_time":0.1541978691,"remaining_time":0.3547059894},
{"learn":[4.425030004],"iteration":303,"passed_time":0.1546886218,"remaining_time":0.3541555288},
{"learn":[4.422588771],"iteration":304,"passed_time":0.1551617729,"remaining_time":0.3535653514},
{"learn":[4.418936667],"iteration":305,"passed_time":0.1556395244,"remaining_time":0.3529863724},
{"learn":[4.416887976],"iteration":306,"passed_time":0.1561052249,"remaining_time":0.3523808497},
{"learn":[4.413773354],"iteration":307,"passed_time":0.15662439,"remaining_time":0.3518963567},
{"learn":[4.411129391],"iteration":308,"passed_time":0.1572400435,"remaining_time":0.3516274112},
{"learn":[4.40850819],"iteration":309,"passed_time":0.1577652091,"remaining_time":0.3511548203},
{"learn":[4.404880292],"iteration":310,"passed_time":0.1582692429,"remaining_time":0.3506350752},
{"learn":[4.404593827],"iteration":311,"passed_time":0.1587574554,"remaining_time":0.3500805426},
{"learn":[4.402139942],"iteration":312,"passed_time":0.1592808008,"remaining_time":0.3496035469},
{"learn":[4.400284725],"iteration":313,"passed_time":0.1598394594,"remaining_time":0.3492034049},
{"learn":[4.395805521],"iteration":314,"passed_time":0.1603917874,"remaining_time":0.34878849},
{"learn":[4.392838833],"iteration":315,"passed_time":0.1609129627,"remaining_time":0.3483052736},
{"learn":[4.389213061],"iteration":316,"passed_time":0.1615141649,"remaining_time":0.3479942417},
{"learn":[4.3861981],"iteration":317,"passed_time":0.1620550619,"remaining_time":0.347552051},
{"learn":[4.385054234],"iteration":318,"passed_time":0.1625594457,"remaining_time":0.3470312932},
{"learn":[4.379364607],"iteration":319,"passed_time":0.16306891,"remaining_time":0.3465214337},
{"learn":[4.378387619],"iteration":320,"passed_time":0.1635535721,"remaining_time":0.3459591136},
{"learn":[4.375816727],"iteration":321,"passed_time":0.164050405,"remaining_time":0.3454229025},
{"learn":[4.374600202],"iteration":322,"passed_time":0.1645239762,"remaining_time":0.3448381792},
{"learn":[4.37098897],"iteration":323,"passed_time":0.1650008876,"remaining_time":0.3442611112},
{"learn":[4.367418484],"iteration":324,"passed_time":0.1654977008,"remaining_time":0.3437259939},
{"learn":[4.363584638],"iteration":325,"passed_time":0.1659868433,"remaining_time":0.3431752527},
{"learn":[4.360770706],"iteration":326,"passed_time":0.166478086,"remaining_time":0.3426292106},
{"learn":[4.358675808],"iteration":327,"passed_time":0.1669602479,"remaining_time":0.3420648981},
{"learn":[4.354228195],"iteration":328,"passed_time":0.1674400796,"remaining_time":0.3414963325},
{"learn":[4.353773425],"iteration":329,"passed_time":0.1679023097,"remaining_time":0.3408925683},
{"learn":[4.351648009],"iteration":330,"passed_time":0.1683672101,"remaining_time":0.3402950561},
{"learn":[4.348209927],"iteration":331,"passed_time":0.1688360509,"remaining_time":0.339706271},
{"learn":[4.345852733],"iteration":332,"passed_time":0.1693155525,"remaining_time":0.3391395602},
{"learn":[4.34237339],"iteration":333,"passed_time":0.1697846733,"remaining_time":0.3385526719},
{"learn":[4.340814362],"iteration":334,"passed_time":0.1702406629,"remaining_time":0.3379404204},
{"learn":[4.339707068],"iteration":335,"passed_time":0.1707035032,"remaining_time":0.3373426372},
{"learn":[4.335430786],"iteration":336,"passed_time":0.1711742141,"remaining_time":0.3367611392},
{"learn":[4.33521887],"iteration":337,"passed_time":0.1716098119,"remaining_time":0.3361115251},
{"learn":[4.328507238],"iteration":338,"passed_time":0.1721366077,"remaining_time":0.3356409961},
{"learn":[4.326140732],"iteration":339,"passed_time":0.17262396,"remaining_time":0.3350935695},
{"learn":[4.323785636],"iteration":340,"passed_time":0.1730860402,"remaining_time":0.3344976554},
{"learn":[4.320632534],"iteration":341,"passed_time":0.1735492404,"remaining_time":0.333904679},
{"learn":[4.31973724],"iteration":342,"passed_time":0.1740026698,"remaining_time":0.3332937437},
{"learn":[4.318000924],"iteration":343,"passed_time":0.1744827816,"remaining_time":0.3327346067},
{"learn":[4.312713628],"iteration":344,"passed_time":0.1749529824,"remaining_time":0.3321571115},
{"learn":[4.308220789],"iteration":345,"passed_time":0.1755185816,"remaining_time":0.3317605559},
{"learn":[4.305890947],"iteration":346,"passed_time":0.1760265957,"remaining_time":0.3312546599},
{"learn":[4.305137856],"iteration":347,"passed_time":0.1765074875,"remaining_time":0.3306979363},
{"learn":[4.304787172],"iteration":348,"passed_time":0.1769765583,"remaining_time":0.3301195972},
{"learn":[4.30350134],"iteration":349,"passed_time":0.1775983273,"remaining_time":0.329825465},
{"learn":[4.30293809],"iteration":350,"passed_time":0.1780910001,"remaining_time":0.3292907666},
{"learn":[4.299548459],"iteration":351,"passed_time":0.1785665114,"remaining_time":0.3287247142},
{"learn":[4.294768408],"iteration":352,"passed_time":0.1790430928,"remaining_time":0.3281611361},
{"learn":[4.294581479],"iteration":353,"passed_time":0.1794989624,"remaining_time":0.3275602535},
{"learn":[4.292551604],"iteration":354,"passed_time":0.1799551521,"remaining_time":0.3269607693},
{"learn":[4.288628894],"iteration":355,"passed_time":0.1804239128,"remaining_time":0.326384831},
{"learn":[4.287802767],"iteration":356,"passed_time":0.1808853029,"remaining_time":0.3257962178},
{"learn":[4.284566905],"iteration":357,"passed_time":0.1813566139,"remaining_time":0.3252261064},
{"learn":[4.27890232],"iteration":358,"passed_time":0.1818198341,"remaining_time":0.3246420993},
{"learn":[4.276938023],"iteration":359,"passed_time":0.1822749437,"remaining_time":0.3240443443},
{"learn":[4.273425094],"iteration":360,"passed_time":0.1827491649,"remaining_time":0.3234812087},
{"learn":[4.269726505],"iteration":361,"passed_time":0.1832061046,"remaining_time":0.322888107},
{"learn":[4.265565857],"iteration":362,"passed_time":0.1836897166,"remaining_time":0.3223425605},
{"learn":[4.262117173],"iteration":363,"passed_time":0.184223403,"remaining_time":0.321884847},
{"learn":[4.259185148],"iteration":364,"passed_time":0.1847342974,"remaining_time":0.3213870653},
{"learn":[4.257668507],"iteration":365,"passed_time":0.1852461318,"remaining_time":0.3208908404},
{"learn":[4.253432436],"iteration":366,"passed_time":0.1857227333,"remaining_time":0.3203337606},
{"learn":[4.250216667],"iteration":367,"passed_time":0.1862243368,"remaining_time":0.3198200568},
{"learn":[4.24514828],"iteration":368,"passed_time":0.1867290107,"remaining_time":0.3193116687},
{"learn":[4.244015772],"iteration":369,"passed_time":0.1871902608,"remaining_time":0.3187293629},
{"learn":[4.240329192],"iteration":370,"passed_time":0.1876556912,"remaining_time":0.3181547973},
{"learn":[4.236718014],"iteration":371,"passed_time":0.1881239519,"remaining_time":0.3175855962},
{"learn":[4.233495944],"iteration":372,"passed_time":0.1885911125,"remaining_time":0.3170150872},
{"learn":[4.230357491],"iteration":373,"passed_time":0.1890556029,"remaining_time":0.3164406615},
{"learn":[4.227381215],"iteration":374,"passed_time":0.1895347945,"remaining_time":0.3158913242},
{"learn":[4.226169067],"iteration":375,"passed_time":0.1900190266,"remaining_time":0.315350725},
{"learn":[4.225963861],"iteration":376,"passed_time":0.1904661154,"remaining_time":0.3147490449},
{"learn":[4.224346548],"iteration":377,"passed_time":0.1909225151,"remaining_time":0.3141635037},
{"learn":[4.222595381],"iteration":378,"passed_time":0.1913885156,"remaining_time":0.3135943751},
{"learn":[4.219700938],"iteration":379,"passed_time":0.1918516358,"remaining_time":0.31302109},
{"learn":[4.216356207],"iteration":380,"passed_time":0.1923279672,"remaining_time":0.312469847},
{"learn":[4.214326494],"iteration":381,"passed_time":0.192797038,"remaining_time":0.3119072499},
{"learn":[4.212901398],"iteration":382,"passed_time":0.1932613583,"remaining_time":0.3113374885},
{"learn":[4.211331091],"iteration":383,"passed_time":0.1937238685,"remaining_time":0.3107653724},
{"learn":[4.208624791],"iteration":384,"passed_time":0.1941923992,"remaining_time":0.3102034429},
{"learn":[4.204659106],"iteration":385,"passed_time":0.1946466187,"remaining_time":0.3096192329},
{"learn":[4.202968852],"iteration":386,"passed_time":0.1950933375,"remaining_time":0.3090238137},
{"learn":[4.197261935],"iteration":387,"passed_time":0.1955544876,"remaining_time":0.3084519237},
{"learn":[4.196934403],"iteration":388,"passed_time":0.1960452502,"remaining_time":0.3079271154},
{"learn":[4.192479929],"iteration":389,"passed_time":0.196548354,"remaining_time":0.3074217844},
{"learn":[4.190243116],"iteration":390,"passed_time":0.1971078176,"remaining_time":0.3070042478},
{"learn":[4.185852431],"iteration":391,"passed_time":0.1976213222,"remaining_time":0.3065147038},
{"learn":[4.180967944],"iteration":392,"passed_time":0.1980931832,"remaining_time":0.3059607181},
{"learn":[4.178283162],"iteration":393,"passed_time":0.1986034775,"remaining_time":0.3054662624},
{"learn":[4.176341157],"iteration":394,"passed_time":0.1990827792,"remaining_time":0.3049242567},
{"learn":[4.176041504],"iteration":395,"passed_time":0.199517947,"remaining_time":0.3043152525},
{"learn":[4.175564513],"iteration":396,"passed_time":0.1999693062,"remaining_time":0.303731717},
{"learn":[4.170830274],"iteration":397,"passed_time":0.2004364868,"remaining_time":0.3031727765},
{"learn":[4.167804808],"iteration":398,"passed_time":0.2008931665,"remaining_time":0.3025984789},
{"learn":[4.165860548],"iteration":399,"passed_time":0.2013608971,"remaining_time":0.3020413457},
{"learn":[4.160950571],"iteration":400,"passed_time":0.2018181169,"remaining_time":0.3014689576},
{"learn":[4.158544115],"iteration":401,"passed_time":0.2022816972,"remaining_time":0.3009066042},
{"learn":[4.154448767],"iteration":402,"passed_time":0.2027375768,"remaining_time":0.3003333333},
{"learn":[4.15197457],"iteration":403,"passed_time":0.2032043773,"remaining_time":0.2997767547},
{"learn":[4.149562679],"iteration":404,"passed_time":0.2036529163,"remaining_time":0.2991937906},
{"learn":[4.149327961],"iteration":405,"passed_time":0.2041928435,"remaining_time":0.2987451947},
{"learn":[4.147444889],"iteration":406,"passed_time":0.2046577539,"remaining_time":0.2981868503},
{"learn":[4.147254809],"iteration":407,"passed_time":0.2050985122,"remaining_time":0.2975939197},
{"learn":[4.144589165],"iteration":408,"passed_time":0.2055725934,"remaining_time":0.2970498843},
{"learn":[4.141691034],"iteration":409,"passed_time":0.206039394,"remaining_time":0.2964957132},
{"learn":[4.138893468],"iteration":410,"passed_time":0.206511585,"remaining_time":0.2959496924},
{"learn":[4.136964597],"iteration":411,"passed_time":0.2069727851,"remaining_time":0.2953883437},
{"learn":[4.133773523],"iteration":412,"passed_time":0.2074512266,"remaining_time":0.2948519856},
{"learn":[4.131363444],"iteration":413,"passed_time":0.2080073297,"remaining_time":0.2944258338},
{"learn":[4.130228592],"iteration":414,"passed_time":0.2084878515,"remaining_time":0.2938925135},
{"learn":[4.12884186],"iteration":415,"passed_time":0.2089466213,"remaining_time":0.2933289107},
{"learn":[4.12413494],"iteration":416,"passed_time":0.2094311734,"remaining_time":0.2928018564},
{"learn":[4.119422508],"iteration":417,"passed_time":0.2099165956,"remaining_time":0.2922762168},
{"learn":[4.117038244],"iteration":418,"passed_time":0.2103850563,"remaining_time":0.2917272499},
{"learn":[4.116067631],"iteration":419,"passed_time":0.2108378557,"remaining_time":0.2911570388},
{"learn":[4.110343455],"iteration":420,"passed_time":0.2113054563,"remaining_time":0.2906077415},
{"learn":[4.105604544],"iteration":421,"passed_time":0.2117836978,"remaining_time":0.2900734061},
{"learn":[4.103390131],"iteration":422,"passed_time":0.2122333469,"remaining_time":0.2895003337},
{"learn":[4.096724402],"iteration":423,"passed_time":0.212694347,"remaining_time":0.2889432638},
{"learn":[4.093431279],"iteration":424,"passed_time":0.213154517,"remaining_time":0.288385523},
{"learn":[4.091412744],"iteration":425,"passed_time":0.2136028259,"remaining_time":0.2878122584},
{"learn":[4.091192901],"iteration":426,"passed_time":0.2140417741,"remaining_time":0.2872270177},
{"learn":[4.088994581],"iteration":427,"passed_time":0.2144835825,"remaining_time":0.2866462831},
{"learn":[4.087845355],"iteration":428,"passed_time":0.2149474228,"remaining_time":0.2860955207},
{"learn":[4.083650279],"iteration":429,"passed_time":0.2153965318,"remaining_time":0.2855256352},
{"learn":[4.079840652],"iteration":430,"passed_time":0.2158600721,"remaining_time":0.284975362},
{"learn":[4.075707828],"iteration":431,"passed_time":0.2163511347,"remaining_time":0.2844616772},
{"learn":[4.071345409],"iteration":432,"passed_time":0.2168306264,"remaining_time":0.283932945},
{"learn":[4.067460475],"iteration":433,"passed_time":0.2173225191,"remaining_time":0.2834206125},
{"learn":[4.064914749],"iteration":434,"passed_time":0.2179180009,"remaining_time":0.2830429207},
{"learn":[4.063823175],"iteration":435,"passed_time":0.2184182444,"remaining_time":0.2825410317},
{"learn":[4.058898471],"iteration":436,"passed_time":0.2189290087,"remaining_time":0.2820527046},
{"learn":[4.054120355],"iteration":437,"passed_time":0.2194170512,"remaining_time":0.2815351204},
{"learn":[4.052715901],"iteration":438,"passed_time":0.2199537878,"remaining_time":0.2810798974},
{"learn":[4.052114167],"iteration":439,"passed_time":0.2204692026,"remaining_time":0.2805971669},
{"learn":[4.051377267],"iteration":440,"passed_time":0.2210100746,"remaining_time":0.2801465571},
{"learn":[4.049275336],"iteration":441,"passed_time":0.2215178187,"remaining_time":0.2796537168},
{"learn":[4.047099198],"iteration":442,"passed_time":0.2219968603,"remaining_time":0.2791247205},
{"learn":[4.044348685],"iteration":443,"passed_time":0.2224873129,"remaining_time":0.2786102387},
{"learn":[4.042822379],"iteration":444,"passed_time":0.2229900966,"remaining_time":0.2781112441},
{"learn":[4.041258611],"iteration":445,"passed_time":0.2234702084,"remaining_time":0.2775840705},
{"learn":[4.040044254],"iteration":446,"passed_time":0.2239411693,"remaining_time":0.2770457866},
{"learn":[4.036860137],"iteration":447,"passed_time":0.224420931,"remaining_time":0.2765186471},
{"learn":[4.036372284],"iteration":448,"passed_time":0.2249233046,"remaining_time":0.2760194674},
{"learn":[4.03368231],"iteration":449,"passed_time":0.2253979259,"remaining_time":0.2754863538},
{"learn":[4.032439519],"iteration":450,"passed_time":0.2258727971,"remaining_time":0.274953804},
{"learn":[4.032008634],"iteration":451,"passed_time":0.2263364574,"remaining_time":0.2744079174},
{"learn":[4.030034932],"iteration":452,"passed_time":0.2268183193,"remaining_time":0.2738843723},
{"learn":[4.028173412],"iteration":453,"passed_time":0.2272825196,"remaining_time":0.2733397703},
{"learn":[4.023806097],"iteration":454,"passed_time":0.2277711921,"remaining_time":0.2728248345},
{"learn":[4.020239186],"iteration":455,"passed_time":0.2282579444,"remaining_time":0.2723077231},
{"learn":[4.017384838],"iteration":456,"passed_time":0.2287298254,"remaining_time":0.2717730748},
{"learn":[4.016468229],"iteration":457,"passed_time":0.2292142375,"remaining_time":0.27125353},
{"learn":[4.014530169],"iteration":458,"passed_time":0.2296969694,"remaining_time":0.2707321579},
{"learn":[4.012884822],"iteration":459,"passed_time":0.2301896822,"remaining_time":0.2702226705},
{"learn":[4.008924707],"iteration":460,"passed_time":0.2306578329,"remaining_time":0.2696845378},
{"learn":[4.008286778],"iteration":461,"passed_time":0.2311260236,"remaining_time":0.2691467548},
{"learn":[4.006444202],"iteration":462,"passed_time":0.2316821769,"remaining_time":0.2687112938},
{"learn":[4.003284363],"iteration":463,"passed_time":0.2322620573,"remaining_time":0.2683027214},
{"learn":[3.999811484],"iteration":464,"passed_time":0.2328723804,"remaining_time":0.2679284376},
{"learn":[3.997483319],"iteration":465,"passed_time":0.2333644431,"remaining_time":0.2674176237},
{"learn":[3.99708333],"iteration":466,"passed_time":0.2338306236,"remaining_time":0.2668773499},
{"learn":[3.995860263],"iteration":467,"passed_time":0.2342900135,"remaining_time":0.2663296735},
{"learn":[3.994131111],"iteration":468,"passed_time":0.2347573542,"remaining_time":0.2657913754},
{"learn":[3.993125499],"iteration":469,"passed_time":0.2352223746,"remaining_time":0.2652507628},
{"learn":[3.992954084],"iteration":470,"passed_time":0.2356683533,"remaining_time":0.2646890847},
{"learn":[3.990635743],"iteration":471,"passed_time":0.2361315536,"remaining_time":0.2641471616},
{"learn":[3.986678254],"iteration":472,"passed_time":0.2365974741,"remaining_time":0.2636086022},
{"learn":[3.986393291],"iteration":473,"passed_time":0.2370314618,"remaining_time":0.2630349133},
{"learn":[3.986152671],"iteration":474,"passed_time":0.2374672696,"remaining_time":0.2624638243},
{"learn":[3.985596662],"iteration":475,"passed_time":0.2379150686,"remaining_time":0.261906504},
{"learn":[3.983853457],"iteration":476,"passed_time":0.2384028209,"remaining_time":0.2613934494},
{"learn":[3.983263928],"iteration":477,"passed_time":0.2388379187,"remaining_time":0.2608229991},
{"learn":[3.980067202],"iteration":478,"passed_time":0.2392946184,"remaining_time":0.26027661},
{"learn":[3.978115407],"iteration":479,"passed_time":0.2397626291,"remaining_time":0.2597428482},
{"learn":[3.972661644],"iteration":480,"passed_time":0.240209858,"remaining_time":0.2591869361},
{"learn":[3.969938254],"iteration":481,"passed_time":0.2406724882,"remaining_time":0.2586480267},
{"learn":[3.968211434],"iteration":482,"passed_time":0.2411158467,"remaining_time":0.2580888048},
{"learn":[3.966113368],"iteration":483,"passed_time":0.2415894978,"remaining_time":0.2575623572},
{"learn":[3.962246044],"iteration":484,"passed_time":0.2420754001,"remaining_time":0.2570491362},
{"learn":[3.961319703],"iteration":485,"passed_time":0.2425492612,"remaining_time":0.2565232928},
{"learn":[3.96078191],"iteration":486,"passed_time":0.2430059309,"remaining_time":0.2559795535},
{"learn":[3.958913633],"iteration":487,"passed_time":0.2437040666,"remaining_time":0.2556895125},
{"learn":[3.957428286],"iteration":488,"passed_time":0.2442091805,"remaining_time":0.2551960966},
{"learn":[3.952641965],"iteration":489,"passed_time":0.2446946627,"remaining_time":0.2546821999},
{"learn":[3.951486786],"iteration":490,"passed_time":0.2451852953,"remaining_time":0.2541737583},
{"learn":[3.94938344],"iteration":491,"passed_time":0.2456906192,"remaining_time":0.2536805581},
{"learn":[3.947297924],"iteration":492,"passed_time":0.2461810218,"remaining_time":0.2531719636},
{"learn":[3.946284886],"iteration":493,"passed_time":0.2466906261,"remaining_time":0.252683111},
{"learn":[3.943288204],"iteration":494,"passed_time":0.247184389,"remaining_time":0.252178013},
{"learn":[3.943076488],"iteration":495,"passed_time":0.2476605204,"remaining_time":0.2516550449},
{"learn":[3.942347078],"iteration":496,"passed_time":0.2481419622,"remaining_time":0.2511376398},
{"learn":[3.940251541],"iteration":497,"passed_time":0.2486262243,"remaining_time":0.2506232221},
{"learn":[3.939011019],"iteration":498,"passed_time":0.2491261777,"remaining_time":0.2501246795},
{"learn":[3.938760512],"iteration":499,"passed_time":0.2496026692,"remaining_time":0.2496026692},
{"learn":[3.934522727],"iteration":500,"passed_time":0.2501311151,"remaining_time":0.2491325877},
{"learn":[3.930091193],"iteration":501,"passed_time":0.2506075265,"remaining_time":0.2486106538},
{"learn":[3.927671752],"iteration":502,"passed_time":0.2510889183,"remaining_time":0.2480938219},
{"learn":[3.927280041],"iteration":503,"passed_time":0.2515892618,"remaining_time":0.2475957814},
{"learn":[3.925987561],"iteration":504,"passed_time":0.2520514419,"remaining_time":0.2470603243},
{"learn":[3.921645957],"iteration":505,"passed_time":0.2525176225,"remaining_time":0.2465290622},
{"learn":[3.920333743],"iteration":506,"passed_time":0.2529665515,"remaining_time":0.2459812818},
{"learn":[3.918659461],"iteration":507,"passed_time":0.2534183107,"remaining_time":0.2454366316},
{"learn":[3.916124385],"iteration":508,"passed_time":0.2538674397,"remaining_time":0.2448898093},
{"learn":[3.913849268],"iteration":509,"passed_time":0.2543260296,"remaining_time":0.2443524598},
{"learn":[3.912826119],"iteration":510,"passed_time":0.2547834893,"remaining_time":0.2438143372},
{"learn":[3.910034145],"iteration":511,"passed_time":0.2552919135,"remaining_time":0.2433251051},
{"learn":[3.90792379],"iteration":512,"passed_time":0.2558280398,"remaining_time":0.2428620963},
{"learn":[3.907823851],"iteration":513,"passed_time":0.2563011615,"remaining_time":0.2423392305},
{"learn":[3.904527401],"iteration":514,"passed_time":0.2568282568,"remaining_time":0.2418673874},
{"learn":[3.903378283],"iteration":515,"passed_time":0.2573769947,"remaining_time":0.2414156307},
{"learn":[3.902170135],"iteration":516,"passed_time":0.2578622469,"remaining_time":0.2409041881},
{"learn":[3.899435429],"iteration":517,"passed_time":0.2583618303,"remaining_time":0.2404061819},
{"learn":[3.897497505],"iteration":518,"passed_time":0.2588521829,"remaining_time":0.2398996146},
{"learn":[3.896426119],"iteration":519,"passed_time":0.2593295144,"remaining_time":0.2393810902},
{"learn":[3.896044669],"iteration":520,"passed_time":0.2598211071,"remaining_time":0.2388758355},
{"learn":[3.892795942],"iteration":521,"passed_time":0.2603015288,"remaining_time":0.2383604038},
{"learn":[3.892413888],"iteration":522,"passed_time":0.2609699169,"remaining_time":0.2380165399},
{"learn":[3.891738985],"iteration":523,"passed_time":0.2615788398,"remaining_time":0.2376174194},
{"learn":[3.88822057],"iteration":524,"passed_time":0.2621940333,"remaining_time":0.237223173},
{"learn":[3.883837053],"iteration":525,"passed_time":0.2627903751,"remaining_time":0.2368110985},
{"learn":[3.881769742],"iteration":526,"passed_time":0.2633914273,"remaining_time":0.2364025524},
{"learn":[3.880356898],"iteration":527,"passed_time":0.2639949198,"remaining_time":0.2359954586},
{"learn":[3.879250273],"iteration":528,"passed_time":0.2645068943,"remaining_time":0.2355061384},
{"learn":[3.877174493],"iteration":529,"passed_time":0.264998517,"remaining_time":0.2349986849},
{"learn":[3.875854201],"iteration":530,"passed_time":0.2654781987,"remaining_time":0.2344807442},
{"learn":[3.873189396],"iteration":531,"passed_time":0.2659477695,"remaining_time":0.2339540528},
{"learn":[3.871583368],"iteration":532,"passed_time":0.2664499031,"remaining_time":0.2334561065},
{"learn":[3.869622679],"iteration":533,"passed_time":0.2669507266,"remaining_time":0.2329570011},
{"learn":[3.866860164],"iteration":534,"passed_time":0.2675201458,"remaining_time":0.2325175099},
{"learn":[3.864498444],"iteration":535,"passed_time":0.2680249597,"remaining_time":0.2320216069},
{"learn":[3.861416322],"iteration":536,"passed_time":0.2685032813,"remaining_time":0.2315028291},
{"learn":[3.860265769],"iteration":537,"passed_time":0.2689745922,"remaining_time":0.2309781814},
{"learn":[3.859328725],"iteration":538,"passed_time":0.2694256714,"remaining_time":0.2304364277},
{"learn":[3.858521278],"iteration":539,"passed_time":0.2698788908,"remaining_time":0.2298968329},
{"learn":[3.85599111],"iteration":540,"passed_time":0.2703538121,"remaining_time":0.22937597},
{"learn":[3.852379816],"iteration":541,"passed_time":0.2708324537,"remaining_time":0.2288584203},
{"learn":[3.851327537],"iteration":542,"passed_time":0.2712922336,"remaining_time":0.2283251395},
{"learn":[3.847854898],"iteration":543,"passed_time":0.271757204,"remaining_time":0.2277964798},
{"learn":[3.847083414],"iteration":544,"passed_time":0.2722081932,"remaining_time":0.2272563815},
{"learn":[3.845397429],"iteration":545,"passed_time":0.2726615726,"remaining_time":0.226718597},
{"learn":[3.841933528],"iteration":546,"passed_time":0.273126663,"remaining_time":0.2261908197},
{"learn":[3.840996474],"iteration":547,"passed_time":0.2735945437,"remaining_time":0.2256655725},
{"learn":[3.838355966],"iteration":548,"passed_time":0.2740745854,"remaining_time":0.2251505246},
{"learn":[3.83342799],"iteration":549,"passed_time":0.2745411359,"remaining_time":0.2246245658},
{"learn":[3.828161535],"iteration":550,"passed_time":0.2750465399,"remaining_time":0.2241304835},
{"learn":[3.823502399],"iteration":551,"passed_time":0.2755211511,"remaining_time":0.223611369},
{"learn":[3.820068862],"iteration":552,"passed_time":0.2760157741,"remaining_time":0.2231085913},
{"learn":[3.817951642],"iteration":553,"passed_time":0.2764687434,"remaining_time":0.2225723097},
{"learn":[3.815785958],"iteration":554,"passed_time":0.276935704,"remaining_time":0.2220475465},
{"learn":[3.81503012],"iteration":555,"passed_time":0.2773850931,"remaining_time":0.2215089592},
{"learn":[3.813529315],"iteration":556,"passed_time":0.277856274,"remaining_time":0.220988024},
{"learn":[3.808881326],"iteration":557,"passed_time":0.2783707487,"remaining_time":0.2205015608},
{"learn":[3.808740434],"iteration":558,"passed_time":0.2788273284,"remaining_time":0.2199693235},
{"learn":[3.80714352],"iteration":559,"passed_time":0.2793105804,"remaining_time":0.2194583132},
{"learn":[3.80573346],"iteration":560,"passed_time":0.2798037632,"remaining_time":0.218955173},
{"learn":[3.803370052],"iteration":561,"passed_time":0.2802868152,"remaining_time":0.2184441727},
{"learn":[3.803215211],"iteration":562,"passed_time":0.2807716373,"remaining_time":0.2179346457},
{"learn":[3.801309667],"iteration":563,"passed_time":0.2812494889,"remaining_time":0.2174198176},
{"learn":[3.800003847],"iteration":564,"passed_time":0.281711759,"remaining_time":0.2168931242},
{"learn":[3.798026138],"iteration":565,"passed_time":0.2821625882,"remaining_time":0.2163578857},
{"learn":[3.794745847],"iteration":566,"passed_time":0.2826178078,"remaining_time":0.2158262976},
{"learn":[3.794312041],"iteration":567,"passed_time":0.2830816381,"remaining_time":0.2153015275},
{"learn":[3.792205926],"iteration":568,"passed_time":0.2835488087,"remaining_time":0.2147795018},
{"learn":[3.788991061],"iteration":569,"passed_time":0.2840155392,"remaining_time":0.2142573366},
{"learn":[3.787391572],"iteration":570,"passed_time":0.2844834599,"remaining_time":0.2137362597},
{"learn":[3.7826445],"iteration":571,"passed_time":0.2849525306,"remaining_time":0.2132162292},
{"learn":[3.781700331],"iteration":572,"passed_time":0.2854109705,"remaining_time":0.2126884544},
{"learn":[3.780045374],"iteration":573,"passed_time":0.2858857117,"remaining_time":0.2121730195},
{"learn":[3.775462644],"iteration":574,"passed_time":0.2863366609,"remaining_time":0.2116401407},
{"learn":[3.773711943],"iteration":575,"passed_time":0.2868108221,"remaining_time":0.211124633},
{"learn":[3.772415806],"iteration":576,"passed_time":0.287281393,"remaining_time":0.2106066365},
{"learn":[3.770170875],"iteration":577,"passed_time":0.2877333423,"remaining_time":0.2100752084},
{"learn":[3.765166479],"iteration":578,"passed_time":0.2881877618,"remaining_time":0.209545851},
{"learn":[3.763976102],"iteration":579,"passed_time":0.288650442,"remaining_time":0.2090227338},
{"learn":[3.760761708],"iteration":580,"passed_time":0.2891545358,"remaining_time":0.208529691},
{"learn":[3.758155662],"iteration":581,"passed_time":0.2896822716,"remaining_time":0.2080535903},
{"learn":[3.756844548],"iteration":582,"passed_time":0.2901850153,"remaining_time":0.2075594363},
{"learn":[3.753098923],"iteration":583,"passed_time":0.2907275825,"remaining_time":0.2070936204},
{"learn":[3.751618946],"iteration":584,"passed_time":0.2913224842,"remaining_time":0.2066646683},
{"learn":[3.751398464],"iteration":585,"passed_time":0.2919557689,"remaining_time":0.2062622668},
{"learn":[3.749920103],"iteration":586,"passed_time":0.2924969565,"remaining_time":0.2057942811},
{"learn":[3.748237465],"iteration":587,"passed_time":0.2930161913,"remaining_time":0.2053106647},
{"learn":[3.746021536],"iteration":588,"passed_time":0.2935404269,"remaining_time":0.2048304167},
{"learn":[3.74417648],"iteration":589,"passed_time":0.2940375501,"remaining_time":0.2043311789},
{"learn":[3.738788389],"iteration":590,"passed_time":0.2945226322,"remaining_time":0.2038236152},
{"learn":[3.736021611],"iteration":591,"passed_time":0.2949961134,"remaining_time":0.2033081322},
{"learn":[3.734546151],"iteration":592,"passed_time":0.295486576,"remaining_time":0.2028044459},
{"learn":[3.733527479],"iteration":593,"passed_time":0.2959559768,"remaining_time":0.2022864084},
{"learn":[3.733026392],"iteration":594,"passed_time":0.2964121464,"remaining_time":0.2017595282},
{"learn":[3.730314752],"iteration":595,"passed_time":0.2968951084,"remaining_time":0.2012510466},
{"learn":[3.727342596],"iteration":596,"passed_time":0.297385571,"remaining_time":0.2007477138},
{"learn":[3.725459604],"iteration":597,"passed_time":0.2978536117,"remaining_time":0.200229351},
{"learn":[3.723158842],"iteration":598,"passed_time":0.2983262328,"remaining_time":0.1997142226},
{"learn":[3.722362756],"iteration":599,"passed_time":0.2988033942,"remaining_time":0.1992022628},
{"learn":[3.721443615],"iteration":600,"passed_time":0.2992904465,"remaining_time":0.1986969853},
{"learn":[3.720743486],"iteration":601,"passed_time":0.2997650378,"remaining_time":0.19818353},
{"learn":[3.720215334],"iteration":602,"passed_time":0.300227848,"remaining_time":0.1976624472},
{"learn":[3.719436563],"iteration":603,"passed_time":0.3006827875,"remaining_time":0.1971363971},
{"learn":[3.715046574],"iteration":604,"passed_time":0.3011474179,"remaining_time":0.1966169092},
{"learn":[3.71443396],"iteration":605,"passed_time":0.3016078479,"remaining_time":0.1960948714},
{"learn":[3.712938941],"iteration":606,"passed_time":0.3020749285,"remaining_time":0.1955773425},
{"learn":[3.712814764],"iteration":607,"passed_time":0.3025136666,"remaining_time":0.1950417061},
{"learn":[3.71235348],"iteration":608,"passed_time":0.3030041393,"remaining_time":0.1945396034},
{"learn":[3.711223749],"iteration":609,"passed_time":0.3035184339,"remaining_time":0.1940527692},
{"learn":[3.710755648],"iteration":610,"passed_time":0.3040170173,"remaining_time":0.1935558424},
{"learn":[3.708668039],"iteration":611,"passed_time":0.3045276516,"remaining_time":0.1930665504},
{"learn":[3.705623591],"iteration":612,"passed_time":0.3050353158,"remaining_time":0.1925753135},
{"learn":[3.704045802],"iteration":613,"passed_time":0.3055267685,"remaining_time":0.1920738316},
{"learn":[3.699915209],"iteration":614,"passed_time":0.3060436634,"remaining_time":0.1915883096},
{"learn":[3.696182221],"iteration":615,"passed_time":0.3065326959,"remaining_time":0.1910853169},
{"learn":[3.694263278],"iteration":616,"passed_time":0.3069975363,"remaining_time":0.1905673523},
{"learn":[3.693810229],"iteration":617,"passed_time":0.3074523058,"remaining_time":0.1900433346},
{"learn":[3.690900932],"iteration":618,"passed_time":0.3079180963,"remaining_time":0.1895263242},
{"learn":[3.688020895],"iteration":619,"passed_time":0.3083935176,"remaining_time":0.1890153817},
{"learn":[3.685491894],"iteration":620,"passed_time":0.3088550977,"remaining_time":0.1884961063},
{"learn":[3.684328128],"iteration":621,"passed_time":0.3092972561,"remaining_time":0.1879652135},
{"learn":[3.680640153],"iteration":622,"passed_time":0.3097551759,"remaining_time":0.1874441434},
{"learn":[3.678932783],"iteration":623,"passed_time":0.3102309872,"remaining_time":0.1869340564},
{"learn":[3.674167041],"iteration":624,"passed_time":0.3106828165,"remaining_time":0.1864096899},
{"learn":[3.672200976],"iteration":625,"passed_time":0.3111306654,"remaining_time":0.1858831771},
{"learn":[3.670606604],"iteration":626,"passed_time":0.3115844448,"remaining_time":0.1853604433},
{"learn":[3.665506042],"iteration":627,"passed_time":0.3120544857,"remaining_time":0.1848475616},
{"learn":[3.664214007],"iteration":628,"passed_time":0.312506955,"remaining_time":0.184324452},
{"learn":[3.66261643],"iteration":629,"passed_time":0.3129541239,"remaining_time":0.1837984537},
{"learn":[3.662118449],"iteration":630,"passed_time":0.3133986925,"remaining_time":0.1832711847},
{"learn":[3.660871366],"iteration":631,"passed_time":0.3138497817,"remaining_time":0.1827479742},
{"learn":[3.656695243],"iteration":632,"passed_time":0.3143092816,"remaining_time":0.1822298679},
{"learn":[3.654497801],"iteration":633,"passed_time":0.3147670714,"remaining_time":0.1817109592},
{"learn":[3.654189134],"iteration":634,"passed_time":0.3152647546,"remaining_time":0.1812151739},
{"learn":[3.653957699],"iteration":635,"passed_time":0.3157387358,"remaining_time":0.1807058174},
{"learn":[3.651920725],"iteration":636,"passed_time":0.3162043263,"remaining_time":0.1801917903},
{"learn":[3.65106705],"iteration":637,"passed_time":0.3166765973,"remaining_time":0.1796817057},
{"learn":[3.650612844],"iteration":638,"passed_time":0.3171316269,"remaining_time":0.1791619989},
{"learn":[3.649884732],"iteration":639,"passed_time":0.3177063568,"remaining_time":0.1787098257},
{"learn":[3.646276182],"iteration":640,"passed_time":0.3182108106,"remaining_time":0.1782179111},
{"learn":[3.645808194],"iteration":641,"passed_time":0.3186960128,"remaining_time":0.1777152221},
{"learn":[3.645042989],"iteration":642,"passed_time":0.3192444105,"remaining_time":0.1772476742},
{"learn":[3.639864499],"iteration":643,"passed_time":0.3197638656,"remaining_time":0.176763876},
{"learn":[3.637318478],"iteration":644,"passed_time":0.3202667093,"remaining_time":0.1762708245},
{"learn":[3.636344905],"iteration":645,"passed_time":0.3207501013,"remaining_time":0.1757670834},
{"learn":[3.634754643],"iteration":646,"passed_time":0.3212278928,"remaining_time":0.1752603496},
{"learn":[3.630724975],"iteration":647,"passed_time":0.3217082746,"remaining_time":0.1747551121},
{"learn":[3.629408252],"iteration":648,"passed_time":0.322219979,"remaining_time":0.1742668916},
{"learn":[3.62790646],"iteration":649,"passed_time":0.3227152321,"remaining_time":0.1737697403},
{"learn":[3.627388973],"iteration":650,"passed_time":0.3232015043,"remaining_time":0.1732677803},
{"learn":[3.625163557],"iteration":651,"passed_time":0.3237014378,"remaining_time":0.17277316},
{"learn":[3.623701985],"iteration":652,"passed_time":0.3241921504,"remaining_time":0.1722736236},
{"learn":[3.622342639],"iteration":653,"passed_time":0.3246869434,"remaining_time":0.1717762728},
{"learn":[3.621130639],"iteration":654,"passed_time":0.3251552241,"remaining_time":0.1712649654},
{"learn":[3.619125665],"iteration":655,"passed_time":0.3256454167,"remaining_time":0.1707652795},
{"learn":[3.618878783],"iteration":656,"passed_time":0.3261113372,"remaining_time":0.1702529508},
{"learn":[3.616207429],"iteration":657,"passed_time":0.3265945292,"remaining_time":0.1697497401},
{"learn":[3.61206486],"iteration":658,"passed_time":0.3271198448,"remaining_time":0.1692683871},
{"learn":[3.611955873],"iteration":659,"passed_time":0.3276150478,"remaining_time":0.1687713883},
{"learn":[3.610713743],"iteration":660,"passed_time":0.3281677859,"remaining_time":0.1683039023},
{"learn":[3.610044025],"iteration":661,"passed_time":0.3286712496,"remaining_time":0.1678110006},
{"learn":[3.607342669],"iteration":662,"passed_time":0.329236409,"remaining_time":0.1673494266},
{"learn":[3.602510618],"iteration":663,"passed_time":0.3297477134,"remaining_time":0.1668602887},
{"learn":[3.600492392],"iteration":664,"passed_time":0.3302465168,"remaining_time":0.1663647866},
{"learn":[3.597171065],"iteration":665,"passed_time":0.3307152775,"remaining_time":0.1658542082},
{"learn":[3.594358798],"iteration":666,"passed_time":0.3312184012,"remaining_time":0.165360911},
{"learn":[3.593945251],"iteration":667,"passed_time":0.3317403263,"remaining_time":0.1648769286},
{"learn":[3.593607748],"iteration":668,"passed_time":0.332231719,"remaining_time":0.1643777264},
{"learn":[3.592238714],"iteration":669,"passed_time":0.3327325725,"remaining_time":0.1638832074},
{"learn":[3.590144654],"iteration":670,"passed_time":0.3332271355,"remaining_time":0.1633855851},
{"learn":[3.587151536],"iteration":671,"passed_time":0.3337067072,"remaining_time":0.1628806547},
{"learn":[3.586070865],"iteration":672,"passed_time":0.3341842387,"remaining_time":0.1623748084},
{"learn":[3.585102746],"iteration":673,"passed_time":0.3346664006,"remaining_time":0.1618712857},
{"learn":[3.584362847],"iteration":674,"passed_time":0.3351456622,"remaining_time":0.16136643},
{"learn":[3.581407561],"iteration":675,"passed_time":0.3356201034,"remaining_time":0.1608593395},
{"learn":[3.57919422],"iteration":676,"passed_time":0.3360927745,"remaining_time":0.160351501},
{"learn":[3.577632204],"iteration":677,"passed_time":0.3365733963,"remaining_time":0.1598475422},
{"learn":[3.573911195],"iteration":678,"passed_time":0.3370403269,"remaining_time":0.1593371796},
{"learn":[3.573408216],"iteration":679,"passed_time":0.3374938863,"remaining_time":0.1588206524},
{"learn":[3.571076482],"iteration":680,"passed_time":0.3379615269,"remaining_time":0.1583109061},
{"learn":[3.568177107],"iteration":681,"passed_time":0.3384329179,"remaining_time":0.1578030321},
{"learn":[3.564824621],"iteration":682,"passed_time":0.338929821,"remaining_time":0.1573071058},
{"learn":[3.562475026],"iteration":683,"passed_time":0.339435655,"remaining_time":0.1568153026},
{"learn":[3.561226889],"iteration":684,"passed_time":0.3399197171,"remaining_time":0.1563134465},
{"learn":[3.559383467],"iteration":685,"passed_time":0.3404241609,"remaining_time":0.1558209716},
{"learn":[3.555209766],"iteration":686,"passed_time":0.3409236543,"remaining_time":0.1553262064},
{"learn":[3.55345383],"iteration":687,"passed_time":0.3414047061,"remaining_time":0.1548230644},
{"learn":[3.552300968],"iteration":688,"passed_time":0.341864406,"remaining_time":0.1543103487},
{"learn":[3.551253986],"iteration":689,"passed_time":0.3423413875,"remaining_time":0.1538055509},
{"learn":[3.549807725],"iteration":690,"passed_time":0.3428103582,"remaining_time":0.1532972514},
{"learn":[3.547992926],"iteration":691,"passed_time":0.3432663179,"remaining_time":0.1527832744},
{"learn":[3.545438607],"iteration":692,"passed_time":0.3437469496,"remaining_time":0.1522803947},
{"learn":[3.543313763],"iteration":693,"passed_time":0.3442134302,"remaining_time":0.1517713395},
{"learn":[3.542962896],"iteration":694,"passed_time":0.3446667296,"remaining_time":0.1512566223},
{"learn":[3.539800465],"iteration":695,"passed_time":0.3451246493,"remaining_time":0.1507440997},
{"learn":[3.53953187],"iteration":696,"passed_time":0.3455825591,"remaining_time":0.1502317294},
{"learn":[3.536332425],"iteration":697,"passed_time":0.3461404676,"remaining_time":0.1497627811},
{"learn":[3.534993327],"iteration":698,"passed_time":0.3466021477,"remaining_time":0.1492521409},
{"learn":[3.531637011],"iteration":699,"passed_time":0.3470614076,"remaining_time":0.1487406033},
{"learn":[3.531040284],"iteration":700,"passed_time":0.3475189974,"remaining_time":0.1482285025},
{"learn":[3.529973872],"iteration":701,"passed_time":0.3479738669,"remaining_time":0.1477154022},
{"learn":[3.527325183],"iteration":702,"passed_time":0.3484343469,"remaining_time":0.1472048379},
{"learn":[3.527200815],"iteration":703,"passed_time":0.3488669645,"remaining_time":0.146682701},
{"learn":[3.523459911],"iteration":704,"passed_time":0.3493429259,"remaining_time":0.1461789548},
{"learn":[3.522729934],"iteration":705,"passed_time":0.3498104365,"remaining_time":0.1456717682},
{"learn":[3.522260582],"iteration":706,"passed_time":0.3502573254,"remaining_time":0.1451561476},
{"learn":[3.518641591],"iteration":707,"passed_time":0.3507187755,"remaining_time":0.1446467266},
{"learn":[3.516856405],"iteration":708,"passed_time":0.3512589624,"remaining_time":0.1441697575},
{"learn":[3.515083413],"iteration":709,"passed_time":0.3517565456,"remaining_time":0.1436752088},
{"learn":[3.514671214],"iteration":710,"passed_time":0.3522264865,"remaining_time":0.1431694157},
{"learn":[3.512617621],"iteration":711,"passed_time":0.352704568,"remaining_time":0.1426670163},
{"learn":[3.510747971],"iteration":712,"passed_time":0.3531955307,"remaining_time":0.14216987},
{"learn":[3.508149266],"iteration":713,"passed_time":0.3536794327,"remaining_time":0.1416699128},
{"learn":[3.504557165],"iteration":714,"passed_time":0.3541591144,"remaining_time":0.1411683183},
{"learn":[3.501367208],"iteration":715,"passed_time":0.354649567,"remaining_time":0.1406710573},
{"learn":[3.497593362],"iteration":716,"passed_time":0.3551703723,"remaining_time":0.1401857955},
{"learn":[3.496291169],"iteration":717,"passed_time":0.3556651753,"remaining_time":0.139690222},
{"learn":[3.49330374],"iteration":718,"passed_time":0.3561361262,"remaining_time":0.1391853289},
{"learn":[3.490044385],"iteration":719,"passed_time":0.3566660122,"remaining_time":0.1387034492},
{"learn":[3.488891789],"iteration":720,"passed_time":0.3571289825,"remaining_time":0.1381955425},
{"learn":[3.486869081],"iteration":721,"passed_time":0.3576036837,"remaining_time":0.1376922771},
{"learn":[3.486303638],"iteration":722,"passed_time":0.3580835952,"remaining_time":0.1371910869},
{"learn":[3.486035862],"iteration":723,"passed_time":0.358565337,"remaining_time":0.1366906533},
{"learn":[3.482668951],"iteration":724,"passed_time":0.3590526294,"remaining_time":0.1361923767},
{"learn":[3.47820549],"iteration":725,"passed_time":0.3595645639,"remaining_time":0.1357034304},
{"learn":[3.474392283],"iteration":726,"passed_time":0.3600485759,"remaining_time":0.1352039357},
{"learn":[3.472268163],"iteration":727,"passed_time":0.3605999941,"remaining_time":0.1347296681},
{"learn":[3.471209164],"iteration":728,"passed_time":0.361093777,"remaining_time":0.1342337635},
{"learn":[3.470049971],"iteration":729,"passed_time":0.3615896601,"remaining_time":0.1337386414},
{"learn":[3.469078654],"iteration":730,"passed_time":0.3620799927,"remaining_time":0.1332414747},
{"learn":[3.468643292],"iteration":731,"passed_time":0.3625541439,"remaining_time":0.1327384024},
{"learn":[3.468134848],"iteration":732,"passed_time":0.3630703388,"remaining_time":0.1322507237},
{"learn":[3.467820182],"iteration":733,"passed_time":0.3635708222,"remaining_time":0.1317572735},
{"learn":[3.465776156],"iteration":734,"passed_time":0.3640893873,"remaining_time":0.1312703233},
{"learn":[3.463037608],"iteration":735,"passed_time":0.3645931011,"remaining_time":0.1307779602},
{"learn":[3.45965637],"iteration":736,"passed_time":0.3650932645,"remaining_time":0.1302842993},
{"learn":[3.457275091],"iteration":737,"passed_time":0.3655892176,"remaining_time":0.129789126},
{"learn":[3.455522955],"iteration":738,"passed_time":0.3660691393,"remaining_time":0.1292882887},
{"learn":[3.451270508],"iteration":739,"passed_time":0.3665639423,"remaining_time":0.1287927365},
{"learn":[3.450978947],"iteration":740,"passed_time":0.3670156216,"remaining_time":0.1282821133},
{"learn":[3.450608492],"iteration":741,"passed_time":0.3674752115,"remaining_time":0.1277743997},
{"learn":[3.448122004],"iteration":742,"passed_time":0.3679419121,"remaining_time":0.1272692751},
{"learn":[3.445646714],"iteration":743,"passed_time":0.3684118729,"remaining_time":0.1267653756},
{"learn":[3.44411263],"iteration":744,"passed_time":0.3688745431,"remaining_time":0.1262590718},
{"learn":[3.443264164],"iteration":745,"passed_time":0.3693519946,"remaining_time":0.1257579177},
{"learn":[3.439521363],"iteration":746,"passed_time":0.3698208053,"remaining_time":0.1252539006},
{"learn":[3.436809225],"iteration":747,"passed_time":0.3703090978,"remaining_time":0.124756541},
{"learn":[3.435509465],"iteration":748,"passed_time":0.3707939499,"remaining_time":0.1242580526},
{"learn":[3.434450277],"iteration":749,"passed_time":0.371266911,"remaining_time":0.123755637},
{"learn":[3.431786753],"iteration":750,"passed_time":0.3717440925,"remaining_time":0.1232546991},
{"learn":[3.430150302],"iteration":751,"passed_time":0.3722148934,"remaining_time":0.1227517202},
{"learn":[3.42696281],"iteration":752,"passed_time":0.3727135967,"remaining_time":0.1222579793},
{"learn":[3.426870334],"iteration":753,"passed_time":0.3731723766,"remaining_time":0.1217511998},
{"learn":[3.425200309],"iteration":754,"passed_time":0.3736462678,"remaining_time":0.1212494511},
{"learn":[3.423383783],"iteration":755,"passed_time":0.3741303498,"remaining_time":0.1207510653},
{"learn":[3.422752979],"iteration":756,"passed_time":0.3747029393,"remaining_time":0.1202811285},
{"learn":[3.420845924],"iteration":757,"passed_time":0.3752489868,"remaining_time":0.119802447},
{"learn":[3.418917862],"iteration":758,"passed_time":0.3757405097,"remaining_time":0.1193062752},
{"learn":[3.417095735],"iteration":759,"passed_time":0.3762716959,"remaining_time":0.1188226408},
{"learn":[3.414391848],"iteration":760,"passed_time":0.3767920611,"remaining_time":0.1183354831},
{"learn":[3.41426711],"iteration":761,"passed_time":0.377263042,"remaining_time":0.1178328137},
{"learn":[3.411976013],"iteration":762,"passed_time":0.3777777068,"remaining_time":0.1173437962},
{"learn":[3.408614844],"iteration":763,"passed_time":0.3782736799,"remaining_time":0.1168489378},
{"learn":[3.407906721],"iteration":764,"passed_time":0.3787416405,"remaining_time":0.1163454713},
{"learn":[3.407494015],"iteration":765,"passed_time":0.3792213322,"remaining_time":0.1158456811},
{"learn":[3.406287128],"iteration":766,"passed_time":0.3797092546,"remaining_time":0.1153484437},
{"learn":[3.404600442],"iteration":767,"passed_time":0.3801836158,"remaining_time":0.1148471339},
{"learn":[3.404012662],"iteration":768,"passed_time":0.3806509564,"remaining_time":0.1143437854},
{"learn":[3.400398762],"iteration":769,"passed_time":0.3811124465,"remaining_time":0.1138387827},
{"learn":[3.399737714],"iteration":770,"passed_time":0.3815954585,"remaining_time":0.1133402853},
{"learn":[3.399185251],"iteration":771,"passed_time":0.3820708798,"remaining_time":0.1128395863},
{"learn":[3.397245411],"iteration":772,"passed_time":0.3825371703,"remaining_time":0.1123362712},
{"learn":[3.396229831],"iteration":773,"passed_time":0.3829893596,"remaining_time":0.1118289345},
{"learn":[3.394002836],"iteration":774,"passed_time":0.3834660111,"remaining_time":0.1113288419},
{"learn":[3.389617243],"iteration":775,"passed_time":0.3839221907,"remaining_time":0.1108229004},
{"learn":[3.385426488],"iteration":776,"passed_time":0.3843810406,"remaining_time":0.1103178533},
{"learn":[3.385072258],"iteration":777,"passed_time":0.3848219689,"remaining_time":0.1098078112},
{"learn":[3.383842366],"iteration":778,"passed_time":0.3852929898,"remaining_time":0.1093064836},
{"learn":[3.380110746],"iteration":779,"passed_time":0.3857475593,"remaining_time":0.1088005937},
{"learn":[3.378595218],"iteration":780,"passed_time":0.3862258309,"remaining_time":0.1083014814},
{"learn":[3.377371219],"iteration":781,"passed_time":0.3867952003,"remaining_time":0.107827818},
{"learn":[3.375814782],"iteration":782,"passed_time":0.3873252064,"remaining_time":0.107343001},
{"learn":[3.374195887],"iteration":783,"passed_time":0.3878314404,"remaining_time":0.1068515193},
{"learn":[3.373704309],"iteration":784,"passed_time":0.3883380744,"remaining_time":0.1063601096},
{"learn":[3.372971757],"iteration":785,"passed_time":0.3888564092,"remaining_time":0.1058718468},
{"learn":[3.371565136],"iteration":786,"passed_time":0.389372494,"remaining_time":0.1053828986},
{"learn":[3.3700309],"iteration":787,"passed_time":0.389855356,"remaining_time":0.1048849435},
{"learn":[3.368186663],"iteration":788,"passed_time":0.3903371579,"remaining_time":0.1043867431},
{"learn":[3.366710398],"iteration":789,"passed_time":0.3908071187,"remaining_time":0.1038854366},
{"learn":[3.364598042],"iteration":790,"passed_time":0.3912701889,"remaining_time":0.1033823887},
{"learn":[3.36348442],"iteration":791,"passed_time":0.3917371695,"remaining_time":0.1028804688},
{"learn":[3.362001759],"iteration":792,"passed_time":0.39220346,"remaining_time":0.1023784568},
{"learn":[3.361580401],"iteration":793,"passed_time":0.3926611698,"remaining_time":0.1018743085},
{"learn":[3.359543675],"iteration":794,"passed_time":0.3931272503,"remaining_time":0.1013724356},
{"learn":[3.35766119],"iteration":795,"passed_time":0.3936059419,"remaining_time":0.1008738846},
{"learn":[3.354592969],"iteration":796,"passed_time":0.3940821433,"remaining_time":0.1003747492},
{"learn":[3.350985986],"iteration":797,"passed_time":0.3945461936,"remaining_time":0.09987259537},
{"learn":[3.349589624],"iteration":798,"passed_time":0.3950323959,"remaining_time":0.0993761096},
{"learn":[3.349110856],"iteration":799,"passed_time":0.3955011866,"remaining_time":0.09887529665},
{"learn":[3.345315441],"iteration":800,"passed_time":0.3959700973,"remaining_time":0.09837459347},
{"learn":[3.34397474],"iteration":801,"passed_time":0.3964358278,"remaining_time":0.09787318442},
{"learn":[3.343800902],"iteration":802,"passed_time":0.3968826466,"remaining_time":0.09736722464},
{"learn":[3.342329465],"iteration":803,"passed_time":0.3973375762,"remaining_time":0.09686338921},
{"learn":[3.34220347],"iteration":804,"passed_time":0.397796256,"remaining_time":0.09636058376},
{"learn":[3.341279219],"iteration":805,"passed_time":0.3982685071,"remaining_time":0.09586115431},
{"learn":[3.337329521],"iteration":806,"passed_time":0.3988205653,"remaining_time":0.09538087869},
{"learn":[3.336708453],"iteration":807,"passed_time":0.3993383303,"remaining_time":0.0948922765},
{"learn":[3.333252703],"iteration":808,"passed_time":0.3998512149,"remaining_time":0.09440244998},
{"learn":[3.332186769],"iteration":809,"passed_time":0.4003641994,"remaining_time":0.09391258999},
{"learn":[3.330594851],"iteration":810,"passed_time":0.4008261196,"remaining_time":0.09341077262},
{"learn":[3.327867442],"iteration":811,"passed_time":0.4013188824,"remaining_time":0.09291619444},
{"learn":[3.327563111],"iteration":812,"passed_time":0.4018684401,"remaining_time":0.09243468426},
{"learn":[3.326308994],"iteration":813,"passed_time":0.4023347607,"remaining_time":0.09193398708},
{"learn":[3.326249879],"iteration":814,"passed_time":0.4028346241,"remaining_time":0.09144098829},
{"learn":[3.322336238],"iteration":815,"passed_time":0.4033210864,"remaining_time":0.09094495085},
{"learn":[3.320491154],"iteration":816,"passed_time":0.403788557,"remaining_time":0.0904446829},
{"learn":[3.320434271],"iteration":817,"passed_time":0.4042358059,"remaining_time":0.08993999592},
{"learn":[3.319609638],"iteration":818,"passed_time":0.4047030165,"remaining_time":0.08943986078},
{"learn":[3.316182682],"iteration":819,"passed_time":0.4051703671,"remaining_time":0.08893983667},
{"learn":[3.313126612],"iteration":820,"passed_time":0.4056336973,"remaining_time":0.08843901562},
{"learn":[3.311222803],"iteration":821,"passed_time":0.4061106388,"remaining_time":0.08794123321},
{"learn":[3.309627335],"iteration":822,"passed_time":0.4066008814,"remaining_time":0.08744636209},
{"learn":[3.307974895],"iteration":823,"passed_time":0.4070644717,"remaining_time":0.08694580948},
{"learn":[3.307321505],"iteration":824,"passed_time":0.407517541,"remaining_time":0.08644311476},
{"learn":[3.306759087],"iteration":825,"passed_time":0.4079853017,"remaining_time":0.08594363498},
{"learn":[3.30484037],"iteration":826,"passed_time":0.408449292,"remaining_time":0.08544344319},
{"learn":[3.30201994],"iteration":827,"passed_time":0.4089117922,"remaining_time":0.08494302929},
{"learn":[3.299302297],"iteration":828,"passed_time":0.4093674418,"remaining_time":0.08444129378},
{"learn":[3.298132671],"iteration":829,"passed_time":0.4098133105,"remaining_time":0.08393766601},
{"learn":[3.296976183],"iteration":830,"passed_time":0.4102718504,"remaining_time":0.08343675417},
{"learn":[3.293144745],"iteration":831,"passed_time":0.4108113372,"remaining_time":0.08295228925},
{"learn":[3.290284404],"iteration":832,"passed_time":0.4113090705,"remaining_time":0.08245932146},
{"learn":[3.288285745],"iteration":833,"passed_time":0.4118479973,"remaining_time":0.08197454143},
{"learn":[3.286662667],"iteration":834,"passed_time":0.4123486408,"remaining_time":0.08148206675},
{"learn":[3.285692682],"iteration":835,"passed_time":0.4128512645,"remaining_time":0.08098996098},
{"learn":[3.284565611],"iteration":836,"passed_time":0.4134304148,"remaining_time":0.08051273312},
{"learn":[3.283897383],"iteration":837,"passed_time":0.4138962353,"remaining_time":0.08001335337},
{"learn":[3.280712855],"iteration":838,"passed_time":0.4143585755,"remaining_time":0.07951338576},
{"learn":[3.280468341],"iteration":839,"passed_time":0.4147991638,"remaining_time":0.07900936453},
{"learn":[3.277814895],"iteration":840,"passed_time":0.4152631441,"remaining_time":0.07850991666},
{"learn":[3.276316385],"iteration":841,"passed_time":0.4157380854,"remaining_time":0.07801260984},
{"learn":[3.27557063],"iteration":842,"passed_time":0.4161963952,"remaining_time":0.07751225865},
{"learn":[3.27499628],"iteration":843,"passed_time":0.4166447141,"remaining_time":0.07701016043},
{"learn":[3.273569958],"iteration":844,"passed_time":0.4172815292,"remaining_time":0.07654276571},
{"learn":[3.269665595],"iteration":845,"passed_time":0.4178166957,"remaining_time":0.07605646707},
{"learn":[3.267984685],"iteration":846,"passed_time":0.4183203495,"remaining_time":0.07556436065},
{"learn":[3.267702508],"iteration":847,"passed_time":0.4188222031,"remaining_time":0.07507190433},
{"learn":[3.266671924],"iteration":848,"passed_time":0.4193175261,"remaining_time":0.07457826437},
{"learn":[3.265359825],"iteration":849,"passed_time":0.4197820665,"remaining_time":0.07407918821},
{"learn":[3.2618983],"iteration":850,"passed_time":0.4202644984,"remaining_time":0.07358332581},
{"learn":[3.260456253],"iteration":851,"passed_time":0.4207229983,"remaining_time":0.07308333773},
{"learn":[3.258389147],"iteration":852,"passed_time":0.4212091905,"remaining_time":0.07258821923},
{"learn":[3.258108469],"iteration":853,"passed_time":0.4216715907,"remaining_time":0.07208905415},
{"learn":[3.256424936],"iteration":854,"passed_time":0.4221362811,"remaining_time":0.07159036346},
{"learn":[3.254817983],"iteration":855,"passed_time":0.4227262623,"remaining_time":0.07111282918},
{"learn":[3.253898449],"iteration":856,"passed_time":0.4232367367,"remaining_time":0.07062176587},
{"learn":[3.253023652],"iteration":857,"passed_time":0.4237621921,"remaining_time":0.07013313669},
{"learn":[3.252845542],"iteration":858,"passed_time":0.4242761268,"remaining_time":0.0696425307},
{"learn":[3.252316026],"iteration":859,"passed_time":0.4247499679,"remaining_time":0.06914534362},
{"learn":[3.24975301],"iteration":860,"passed_time":0.4253017059,"remaining_time":0.06866078643},
{"learn":[3.249151075],"iteration":861,"passed_time":0.425763706,"remaining_time":0.068161707},
{"learn":[3.246257135],"iteration":862,"passed_time":0.4262647896,"remaining_time":0.06766891793},
{"learn":[3.243826471],"iteration":863,"passed_time":0.4267359305,"remaining_time":0.06717139647},
{"learn":[3.243190653],"iteration":864,"passed_time":0.4271974106,"remaining_time":0.06667242824},
{"learn":[3.24008797],"iteration":865,"passed_time":0.4276476797,"remaining_time":0.06617181187},
{"learn":[3.240036811],"iteration":866,"passed_time":0.4280974288,"remaining_time":0.06567123187},
{"learn":[3.238676314],"iteration":867,"passed_time":0.4285472979,"remaining_time":0.06517078724},
{"learn":[3.237848782],"iteration":868,"passed_time":0.4290006973,"remaining_time":0.06467099119},
{"learn":[3.236405498],"iteration":869,"passed_time":0.4294612673,"remaining_time":0.06417237328},
{"learn":[3.233378068],"iteration":870,"passed_time":0.4299394089,"remaining_time":0.06367644517},
{"learn":[3.233169169],"iteration":871,"passed_time":0.4304602739,"remaining_time":0.06318682919},
{"learn":[3.232434885],"iteration":872,"passed_time":0.4309640876,"remaining_time":0.06269466109},
{"learn":[3.229978115],"iteration":873,"passed_time":0.43145207,"remaining_time":0.06220018401},
{"learn":[3.229648848],"iteration":874,"passed_time":0.4319471631,"remaining_time":0.06170673758},
{"learn":[3.227208761],"iteration":875,"passed_time":0.4324393858,"remaining_time":0.0612128811},
{"learn":[3.226258869],"iteration":876,"passed_time":0.4329206877,"remaining_time":0.06071749667},
{"learn":[3.225331995],"iteration":877,"passed_time":0.4333952189,"remaining_time":0.06022120354},
{"learn":[3.221968268],"iteration":878,"passed_time":0.4338897819,"remaining_time":0.05972771741},
{"learn":[3.221166317],"iteration":879,"passed_time":0.4344097973,"remaining_time":0.05923769964},
{"learn":[3.220047503],"iteration":880,"passed_time":0.4348901491,"remaining_time":0.05874225623},
{"learn":[3.21982781],"iteration":881,"passed_time":0.4353675105,"remaining_time":0.05824644699},
{"learn":[3.216693405],"iteration":882,"passed_time":0.4358552629,"remaining_time":0.05775205636},
{"learn":[3.214798761],"iteration":883,"passed_time":0.4363249237,"remaining_time":0.05725530674},
{"learn":[3.214395085],"iteration":884,"passed_time":0.4367815934,"remaining_time":0.05675693022},
{"learn":[3.213470696],"iteration":885,"passed_time":0.4372477939,"remaining_time":0.05625987416},
{"learn":[3.211595017],"iteration":886,"passed_time":0.4377412568,"remaining_time":0.05576636079},
{"learn":[3.210965255],"iteration":887,"passed_time":0.4382597819,"remaining_time":0.05527600852},
{"learn":[3.209413583],"iteration":888,"passed_time":0.4387650258,"remaining_time":0.0547839346},
{"learn":[3.208331683],"iteration":889,"passed_time":0.4392886213,"remaining_time":0.05429409926},
{"learn":[3.207110711],"iteration":890,"passed_time":0.4397776438,"remaining_time":0.05379995867},
{"learn":[3.204519413],"iteration":891,"passed_time":0.4402660462,"remaining_time":0.05330575447},
{"learn":[3.201421296],"iteration":892,"passed_time":0.4407548987,"remaining_time":0.0528116172},
{"learn":[3.200691259],"iteration":893,"passed_time":0.4412543121,"remaining_time":0.05231874394},
{"learn":[3.200485067],"iteration":894,"passed_time":0.4417274132,"remaining_time":0.05182276915},
{"learn":[3.197467568],"iteration":895,"passed_time":0.4422168457,"remaining_time":0.05132874102},
{"learn":[3.195838544],"iteration":896,"passed_time":0.4427114187,"remaining_time":0.05083531341},
{"learn":[3.195671746],"iteration":897,"passed_time":0.4431658782,"remaining_time":0.05033732692},
{"learn":[3.194213094],"iteration":898,"passed_time":0.4436555607,"remaining_time":0.04984339448},
{"learn":[3.192884691],"iteration":899,"passed_time":0.4441747359,"remaining_time":0.04935274843},
{"learn":[3.188364239],"iteration":900,"passed_time":0.4446657085,"remaining_time":0.04885894023},
{"learn":[3.185219478],"iteration":901,"passed_time":0.4451501906,"remaining_time":0.04836443313},
{"learn":[3.184120387],"iteration":902,"passed_time":0.4456292622,"remaining_time":0.04786936704},
{"learn":[3.183725321],"iteration":903,"passed_time":0.446109204,"remaining_time":0.04737442874},
{"learn":[3.181264554],"iteration":904,"passed_time":0.4466444305,"remaining_time":0.04688532695},
{"learn":[3.180741589],"iteration":905,"passed_time":0.4471539647,"remaining_time":0.04639345771},
{"learn":[3.179782639],"iteration":906,"passed_time":0.4476601187,"remaining_time":0.04590120291},
{"learn":[3.176377564],"iteration":907,"passed_time":0.4481539216,"remaining_time":0.04540766607},
{"learn":[3.174078182],"iteration":908,"passed_time":0.4486403539,"remaining_time":0.04491339076},
{"learn":[3.171242379],"iteration":909,"passed_time":0.4491348269,"remaining_time":0.04441992793},
{"learn":[3.170421012],"iteration":910,"passed_time":0.4496164387,"remaining_time":0.04392520642},
{"learn":[3.170087224],"iteration":911,"passed_time":0.4500986906,"remaining_time":0.04343057541},
{"learn":[3.167303059],"iteration":912,"passed_time":0.4505819526,"remaining_time":0.04293606777},
{"learn":[3.16705966],"iteration":913,"passed_time":0.4510575639,"remaining_time":0.04244086488},
{"learn":[3.165667683],"iteration":914,"passed_time":0.4515429161,"remaining_time":0.04194660969},
{"learn":[3.164689733],"iteration":915,"passed_time":0.4520207076,"remaining_time":0.04145168061},
{"learn":[3.163311455],"iteration":916,"passed_time":0.4525094501,"remaining_time":0.04095778011},
{"learn":[3.159425016],"iteration":917,"passed_time":0.4530412663,"remaining_time":0.04046773839},
{"learn":[3.159327058],"iteration":918,"passed_time":0.4535008263,"remaining_time":0.03997123713},
{"learn":[3.15819426],"iteration":919,"passed_time":0.4539785378,"remaining_time":0.03947639459},
{"learn":[3.157086603],"iteration":920,"passed_time":0.4544622598,"remaining_time":0.0389821048},
{"learn":[3.153354154],"iteration":921,"passed_time":0.4549916761,"remaining_time":0.03849170362},
{"learn":[3.153261317],"iteration":922,"passed_time":0.4554996302,"remaining_time":0.03799942744},
{"learn":[3.153168454],"iteration":923,"passed_time":0.456015465,"remaining_time":0.03750776552},
{"learn":[3.152080399],"iteration":924,"passed_time":0.4565255994,"remaining_time":0.03701558914},
{"learn":[3.151635144],"iteration":925,"passed_time":0.4570578056,"remaining_time":0.03652513781},
{"learn":[3.147762655],"iteration":926,"passed_time":0.4575840513,"remaining_time":0.03603412702},
{"learn":[3.147172317],"iteration":927,"passed_time":0.458239668,"remaining_time":0.03555307769},
{"learn":[3.146254125],"iteration":928,"passed_time":0.458803657,"remaining_time":0.03506464979},
{"learn":[3.144869828],"iteration":929,"passed_time":0.459340874,"remaining_time":0.03457404428},
{"learn":[3.143466218],"iteration":930,"passed_time":0.4598931817,"remaining_time":0.03408445708},
{"learn":[3.141919643],"iteration":931,"passed_time":0.4603940352,"remaining_time":0.03359098111},
{"learn":[3.141054135],"iteration":932,"passed_time":0.4608844479,"remaining_time":0.03309673956},
{"learn":[3.139390417],"iteration":933,"passed_time":0.4613683299,"remaining_time":0.03260204473},
{"learn":[3.139025283],"iteration":934,"passed_time":0.4618283799,"remaining_time":0.03210571625},
{"learn":[3.137824183],"iteration":935,"passed_time":0.4623099817,"remaining_time":0.03161093892},
{"learn":[3.135620453],"iteration":936,"passed_time":0.4627756422,"remaining_time":0.03111511789},
{"learn":[3.13443178],"iteration":937,"passed_time":0.4632713153,"remaining_time":0.03062134493},
{"learn":[3.132765713],"iteration":938,"passed_time":0.4637527171,"remaining_time":0.03012664083},
{"learn":[3.131434124],"iteration":939,"passed_time":0.4642381593,"remaining_time":0.02963222293},
{"learn":[3.128384262],"iteration":940,"passed_time":0.4647197111,"remaining_time":0.02913758019},
{"learn":[3.128120455],"iteration":941,"passed_time":0.4651959925,"remaining_time":0.02864264073},
{"learn":[3.126314615],"iteration":942,"passed_time":0.4656822948,"remaining_time":0.02814834656},
{"learn":[3.125409666],"iteration":943,"passed_time":0.4661854185,"remaining_time":0.0276550672},
{"learn":[3.123072589],"iteration":944,"passed_time":0.4666765009,"remaining_time":0.02716106619},
{"learn":[3.122921099],"iteration":945,"passed_time":0.4671522222,"remaining_time":0.0266661945},
{"learn":[3.122182662],"iteration":946,"passed_time":0.4676227131,"remaining_time":0.02617107053},
{"learn":[3.120040951],"iteration":947,"passed_time":0.468081743,"remaining_time":0.02567536987},
{"learn":[3.118767799],"iteration":948,"passed_time":0.4685361125,"remaining_time":0.02517949603},
{"learn":[3.118203218],"iteration":949,"passed_time":0.4690168843,"remaining_time":0.02468509917},
{"learn":[3.116343362],"iteration":950,"passed_time":0.4694832548,"remaining_time":0.02418998894},
{"learn":[3.11480829],"iteration":951,"passed_time":0.4699930696,"remaining_time":0.02369712956},
{"learn":[3.112607903],"iteration":952,"passed_time":0.4705411873,"remaining_time":0.02320612361},
{"learn":[3.111661241],"iteration":953,"passed_time":0.4710711528,"remaining_time":0.02271412267},
{"learn":[3.110249676],"iteration":954,"passed_time":0.4716214509,"remaining_time":0.0222230003},
{"learn":[3.107333579],"iteration":955,"passed_time":0.4721209943,"remaining_time":0.02172941815},
{"learn":[3.107149851],"iteration":956,"passed_time":0.4725889449,"remaining_time":0.021234404},
{"learn":[3.106867336],"iteration":957,"passed_time":0.4730666164,"remaining_time":0.02073987254},
{"learn":[3.10364681],"iteration":958,"passed_time":0.4735467682,"remaining_time":0.02024548227},
{"learn":[3.102703811],"iteration":959,"passed_time":0.4740081082,"remaining_time":0.01975033784},
{"learn":[3.101469264],"iteration":960,"passed_time":0.4745167624,"remaining_time":0.01925718391},
{"learn":[3.09863569],"iteration":961,"passed_time":0.4750173259,"remaining_time":0.01876367816},
{"learn":[3.09645939],"iteration":962,"passed_time":0.4754979977,"remaining_time":0.01826939347},
{"learn":[3.096240186],"iteration":963,"passed_time":0.4759683186,"remaining_time":0.01777475049},
{"learn":[3.094838828],"iteration":964,"passed_time":0.4764573911,"remaining_time":0.01728083802},
{"learn":[3.094176802],"iteration":965,"passed_time":0.476917231,"remaining_time":0.01678590668},
{"learn":[3.093182279],"iteration":966,"passed_time":0.4773820914,"remaining_time":0.01629121925},
{"learn":[3.090150687],"iteration":967,"passed_time":0.4778542325,"remaining_time":0.01579683413},
{"learn":[3.088612829],"iteration":968,"passed_time":0.4783141024,"remaining_time":0.01530210235},
{"learn":[3.087153684],"iteration":969,"passed_time":0.478792194,"remaining_time":0.014808006},
{"learn":[3.085866843],"iteration":970,"passed_time":0.4792565343,"remaining_time":0.01431353192},
{"learn":[3.082669094],"iteration":971,"passed_time":0.479759278,"remaining_time":0.01382022612},
{"learn":[3.081047548],"iteration":972,"passed_time":0.4802268286,"remaining_time":0.01332592433},
{"learn":[3.079684322],"iteration":973,"passed_time":0.4807010398,"remaining_time":0.01283185527},
{"learn":[3.07613431],"iteration":974,"passed_time":0.4811764111,"remaining_time":0.0123378567},
{"learn":[3.074005935],"iteration":975,"passed_time":0.4816621834,"remaining_time":0.01184415205},
{"learn":[3.072988853],"iteration":976,"passed_time":0.4821945096,"remaining_time":0.01135155959},
{"learn":[3.072344268],"iteration":977,"passed_time":0.4826766615,"remaining_time":0.01085775721},
{"learn":[3.070654438],"iteration":978,"passed_time":0.4831632038,"remaining_time":0.01036407281},
{"learn":[3.069724506],"iteration":979,"passed_time":0.4836452057,"remaining_time":0.00987031032},
{"learn":[3.067763166],"iteration":980,"passed_time":0.4841237173,"remaining_time":0.009376504208},
{"learn":[3.066737893],"iteration":981,"passed_time":0.4846131798,"remaining_time":0.008882929976},
{"learn":[3.065248174],"iteration":982,"passed_time":0.4850971818,"remaining_time":0.008389269676},
{"learn":[3.063186837],"iteration":983,"passed_time":0.4856436093,"remaining_time":0.007896644054},
{"learn":[3.062880371],"iteration":984,"passed_time":0.4861070396,"remaining_time":0.007402645273},
{"learn":[3.061288645],"iteration":985,"passed_time":0.4866011125,"remaining_time":0.006909143586},
{"learn":[3.059970575],"iteration":986,"passed_time":0.4871048963,"remaining_time":0.006415768644},
{"learn":[3.059576341],"iteration":987,"passed_time":0.4875862181,"remaining_time":0.005922099815},
{"learn":[3.058175919],"iteration":988,"passed_time":0.4880532287,"remaining_time":0.00542829678},
{"learn":[3.056830702],"iteration":989,"passed_time":0.4885338705,"remaining_time":0.00493468556},
{"learn":[3.056336579],"iteration":990,"passed_time":0.4889996009,"remaining_time":0.004440965094},
{"learn":[3.055810414],"iteration":991,"passed_time":0.4894774225,"remaining_time":0.003947398568},
{"learn":[3.055476518],"iteration":992,"passed_time":0.4899191208,"remaining_time":0.00345360911},
{"learn":[3.053331734],"iteration":993,"passed_time":0.4903896417,"remaining_time":0.002960098441},
{"learn":[3.050890374],"iteration":994,"passed_time":0.4908657631,"remaining_time":0.002466662126},
{"learn":[3.04972623],"iteration":995,"passed_time":0.4913302635,"remaining_time":0.00197321391},
{"learn":[3.047217327],"iteration":996,"passed_time":0.4918000743,"remaining_time":0.001479839742},
{"learn":[3.047155483],"iteration":997,"passed_time":0.4922578841,"remaining_time":0.0009864887456},
{"learn":[3.04430671],"iteration":998,"passed_time":0.4927370957,"remaining_time":0.000493230326},
{"learn":[3.042664195],"iteration":999,"passed_time":0.4932025462,"remaining_time":0}
]}